Workbook

Sheet Evidence Matrix
A1: Entity Nature Verification — Documentary Evidence Matrix
A2: Paper ID | B2: Priority | C2: Title | D2: Full Reference (Harvard) | E2: Year | F2: Source Type | G2: Main Research Domain | H2: Research Objective(s) | I2: RO1: Characterise the threat | J2: RO2: Classify approaches and failure modes. Human vs AI | K2: RO3: Verification in Security Frameworks | L2: RO4: Analyse trust asymmetries and risk conditions. | M2: RO5: Integrated ENV Model | N2: Method / Technique | O2: Evidence Source | P2: Text-Based Comm. Context | Q2: AI Involvement | R2: Identity / Impersonation Aspect | S2: Trust Dimension | T2: Results / Key Findings | U2: Search String ID | V2: Notes (Important): | W2: Corpus Status | X2: Identification Route | Y2: Original Source | Z2: Inclusion / Role Rationale | AA2: Evidence Review Status | AB2: Dissertation Use
A3: A003 | B3: P1-CORE | C3: The End of Trust: How Agentic AI Breaks Security Assumptions | D3: Zafar, O., Nemecek, A. and Ayday, E. (2026) The End of Trust: How Agentic AI Breaks Security Assumptions. arXiv preprint arXiv:2605.16436v1 [cs.CR], 14 May. Available at: https://arxiv.org/abs/2605.16436 (Accessed: 14 July 2026). | E3: 2026 | F3: Preprint | G3: Agentic AI / Social Engineering / Security Paradigm Theory | H3: =I3&" "&J3&" "&K3&" "&L3&" "&M3 -> RO1 RO2 RO4 RO5 | I3: RO1 | J3: RO2 | L3: RO4 | M3: RO5 | N3: Conceptual Analysis; Literature Critique; Framework Proposal | O3: Academic Literature; Industry Reports (Europol, NCSC, FBI IC3, FTC, Verizon DBIR 2025) | P3: All text-based digital interaction: email, enterprise messaging, social platforms, organisational communication channels | Q3: Autonomous agentic AI (LLM-backed); generative AI (synthetic text, deepfakes); MitM agent (Infinite Impostor) | R3: Infinite Impostor: autonomous agent interposes between two parties who already trust each other, hijacking existing relationship rather than building new identity; full lifecycle social engineering automation (reconnaissance → persona → exploitation); relationship hijacking without fabricating either party | S3: Collapse of fidelity-scale tradeoff; exhaustion of trust-based security paradigm; suspect-by-default; action-level vs. identity-level evaluation; bounded-damage architecture | T3: Agentic AI eliminates the historical fidelity-scale tradeoff — targeted attacks can now be executed at mass-market scale, dissolving the key assumption underpinning all existing defences. "Infinite Impostor" attack model: agent acts as hidden intermediary between two authentic parties (not a fake identity problem — both endpoints are real). Detection-oriented defences are structurally futile in an asymmetric arms race with improving generative systems. Proposes "suspect-by-default" paradigm: abandon actor authentication in favour of action evaluation + bounded-damage architecture (escrow, rate-limited trust, exposure caps). Critically engages proof-of-humanity (personhood credentials) finding that such systems risk centralization, exclusion, and inverting the presumption of digital citizenship. Four unresolved tensions: Infinite Impostor residual, baseline contamination/measurement problem, cost of universal suspicion, platform governance accountability. | U3: ARXIV-S1 | V3: RO1: Introduces the "Infinite Impostor" attack model, where an autonomous agent inserts itself as a hidden intermediary between two real individuals who already share a trust relationship. The paper explicitly links this attack pathway to organizational threats, explaining how agents harvest data to create context-aware personas that perfectly mimic internal colleagues for Business Email Compromise (BEC) and spear-phishing campaigns RO2: Argues that human-in-the-loop detection and user awareness training are experiencing a paradigmatic failure. Traditional cues (poor grammar, generic greetings, urgency) fail because modern AI successfully mimics the central tendencies, variances, and context-dependent fluctuations of human behavior. Main contribution: The authors argue that Agentic AI collapses the "fidelity-scale tradeoff," enabling high-fidelity, individually tailored deceptions at mass-market scale, which effectively "exhausts" the current security paradigm of detection-based trust.,,. It proposes a transition from identity-centric "trust-based security" to "suspect-by-default" architectures that focus on evaluating and constraining actions rather than authenticating actors. RO4: Explores the "Infinite Impostor" attack model, where an autonomous agent inserts itself as a hidden intermediary between two parties who already trust each other. The paper emphasizes that when entity nature verification fails, the assumption of implicit trust becomes highly exploitable, fundamentally breaking legacy human-centric security paradigms and shifting organizational risk. RO5: Details how agents infiltrate trust-based external communication channels (like social media and professional networks) by constructing convincing, context-aware personas. It illustrates how these fabricated identities are used to launch Business Email Compromise (BEC) and initiate fraudulent internal communications. Strongest citable concept/mechanism/model: The Infinite Impostor,, — An attack model where an autonomous agent operates as a hidden intermediary between two real individuals, hijacking an existing trust relationship rather than building a new persona from scratch.,. Limitation or questionable assumption: The authors acknowledge a "bootstrap and measurement problem," where it may be impossible to create a "legitimate" baseline for action-based evaluation if the system is already infiltrated by synthetic actors at the moment the baseline is drawn.. Additionally, they admit their proposed "action-based evaluation" is limited against the Infinite Impostor, whose relayed communications are structurally indistinguishable from genuine activity.,. Dissertation-ready note: This source is pivotal for RO3 as it argues that the human layer is no longer a viable "last line of defence" because the cues humans use to distinguish authentic from synthetic—such as conversational nuance and response timing—can now be convincingly synthesised (Section IV-B,,). It frames the pursuit of "detecting the fake" as "structurally futile," suggesting that the human-agent distinction is essentially collapsing at the level of digital interaction (Section I,). | W3: Eligible analytical source | X3: Structured database search | Y3: arXiv | Z3: Develops the Infinite Impostor model and explains how agentic AI can exploit established trust relationships in text-based communication, supporting RO1, RO2, RO4 and the ENV problem formulation. | AA3: Full text reviewed | AB3: Analytical contribution
A4: N001 | B4: P2-HIGH | C4: TRiSM for Agentic AI: A review of Trust, Risk, and Security Management in LLM-based Agentic Multi-Agent Systems | D4: Raza, S., Sapkota, R., Karkee, M. and Emmanouilidis, C. (2026) 'TRiSM for agentic AI: a review of trust, risk, and security management in LLM-based agentic multi-agent systems', AI Open, 7, pp. 71–95. Available at: https://doi.org/10.1016/j.aiopen.2026.02.006 | E4: 2026 | F4: Journal Article | G4: Autonomous AI Agents | H4: =I4&" "&J4&" "&K4&" "&L4&" "&M4 -> RO3 RO5 | K4: RO3 | M4: RO5 | N4: Systematic Review | O4: Academic Literature | P4: Enterprise AI | Q4: Multi-Agent LLM | R4: Agent Impersonation; Trust Risk | S4: Trust Management | T4: TRiSM framework identifies impersonation and trust exploitation as top agentic AI risks | U4: GSLABS-01 | V4: RO3: The authors map existing frameworks (NIST AI RMF, ISO/IEC 42001, and the EU AI Act) against multi-agent systems. They note that existing frameworks treat risk domains as distinct and fail to model AMAS-specific dynamics like emergent coordination, delegated authority (autonomy abuse), and tool-mediated actions, proposing an adapted TRiSM framework to fill these verification gaps. RO5: Reviews tailored TRiSM (Trust, Risk, and Security Management) controls for agentic systems. It connects trust decisions directly to organizational governance, accountability, anomaly detection, and role separation. Main contribution: The source develops a system-level Trust, Risk, and Security Management (TRiSM) framework specifically for Agentic Multi-Agent Systems (AMAS), addressing emergent risks such as impersonation, cascading reasoning errors, and tool-use abuse. It introduces novel metrics, including the Component Synergy Score (CSS) and Tool Utilization Efficacy (TUE), to operationalize the measurement of autonomous coordination and security. Strongest citable concept/mechanism/model: Decision Provenance Graph — A structured, graph-based representation that records reasoning steps, data flows, and inter-agent interactions to enable post-hoc auditing and system-level interpretability. Limitation or questionable assumption: The authors acknowledge that human-centered evaluation is "resource-intensive" and fails to scale for continuous deployment, while also noting a potential "Goodhart’s Law" effect where systems might optimize for composite trust scores rather than underlying capability. Additionally, they assume that "explainability" facilitates trust, yet concede that a "faithful" explanation is not always human-interpretable. Dissertation-ready note: This survey explicitly identifies "impersonation" as a coordinated attack vector in multi-agent environments, suggesting that technical authentication must be supplemented by "decision provenance" to allow humans to verify an entity's nature (Section 6.3). It highlights a critical gap: while TRiSM aims for "trust calibration," the resource constraints of human oversight often lead to "automation bias" or "user complacency" (Section 8.2, Section 8.3). | W4: Eligible analytical source | X4: Targeted supplementary search | Y4: Google Scholar Labs | Z4: Reviews trust, risk and security management for agentic multi-agent systems and identifies gaps concerning emergent coordination, delegated authority and tool-mediated action. | AA4: Full text reviewed | AB4: Analytical contribution
A5: N002 | B5: P2-HIGH | C5: Security Analysis of Agentic AI Communication Protocols: A Comparative Evaluation | D5: Louck, Y., Stulman, A. and Dvir, A. (2025) Security Analysis of Agentic AI Communication Protocols: A Comparative Evaluation. arXiv preprint. Available at: https://arxiv.org/abs/2511.03841 (Accessed: 18 July 2026) | E5: 2025 | F5: Preprint | G5: AI Agent Security | H5: =I5&" "&J5&" "&K5&" "&L5&" "&M5 -> RO4 RO5 | L5: RO4 | M5: RO5 | N5: Comparative Evaluation | O5: Empirical Study | P5: Agent-to-Agent Communication | Q5: Multi-Agent | R5: Authentication Bypass; Impersonation | S5: Trust | T5: Protocol-level authentication bypass and agent impersonation vulnerabilities across MCP, A2A, ANP | U5: ARXIV-S8 | V5: RO4: Discusses how the absence of Strong Customer Authentication (SCA) and cryptographic discovery mechanisms allows adversaries to forge identities, impersonate trusted agents, and bypass authorization. RO5: Documents specific vulnerabilities where adversaries forge capabilities and "impersonate trusted agents during dynamic discovery." It highlights how the lack of chain-of-trust enforcement enables spoofing in agent-to-agent (A2A) interactions. Main contribution: The authors provide the first empirical, comparative security analysis of major agent communication protocols (A2A, ACP, and CORAL), identifying a critical "architecture versus implementation" dichotomy where robust designs are undermined by fundamental validation failures. The study concludes that current ecosystems remain largely insecure because they lack a hybrid approach that combines secure transport-layer isolation with mandatory, granular message-level integrity. Strongest citable concept/mechanism/model: 14-point Vulnerability Taxonomy for Multi-Agent Systems — A formal framework that groups threats into five domains (Authentication, Authorization, Integrity, Confidentiality, and Availability) to systematically evaluate how protocols handle autonomous agent interactions. Limitation or questionable assumption: The threat model explicitly excludes "physical access or full compromise of the underlying large language model (LLM)," focusing instead on the communication layer. Consequently, the authors admit that "Prompt & Tool Injection" remains a persistent "application-layer" risk that protocol-level security cannot fully mitigate, as malicious instructions may still be processed as valid by the agent's internal model. Dissertation-ready note: This source is vital for RO3 because it argues that current protocols fail to maintain the distinction between "automated and human oversight," often incorrectly equating technical agent delegation with actual user consent (Section 6.1.2, p. 14). It provides empirical evidence that even "secure" protocols can be exploited via "Spoofing in Discovery Mechanisms," where an attacker manipulates metadata to impersonate a legitimate agent and hijack organizational workflows (Section 6.2.4, p. 20; Section 8.3.2, p. 44). | W5: Eligible analytical source | X5: Structured database search | Y5: arXiv | Z5: Compares agent communication protocols and provides evidence of authentication, discovery and impersonation vulnerabilities affecting inter-agent trust. | AA5: Abstract screened | AB5: Not yet used
A6: N003 | B6: P3-MEDIUM | C6: Infrastructure for AI Agents | D6: Chan, A., Wei, K., Huang, S., Rajkumar, N., Perrier, E., Lazar, S., Hadfield, G.K. and Anderljung, M. (2025) 'Infrastructure for AI Agents', Transactions on Machine Learning Research. Available at: https://openreview.net/pdf?id=Ckh17xN2R2 | E6: 2025 | F6: Journal Article | G6: Autonomous AI Agents | H6: =I6&" "&J6&" "&K6&" "&L6&" "&M6 -> RO5 | M6: RO5 | N6: Framework Proposal | O6: Conceptual Analysis | P6: General AI Infrastructure | Q6: Agentic AI | R6: Identity / Credential Management | S6: Trust | T6: Infrastructure requirements for AI agents including identity verification and credential trust chains | U6: AI-COMP-01 | V6: RO5: Details attribution infrastructure, focusing on identity binding (linking an agent to a legal human or corporate identity) and certification tools for verifying claims about an agent's operation | W6: Eligible analytical source | X6: Targeted supplementary search | Y6: Transactions on Machine Learning Research | Z6: Identifies identity binding, attribution and certification infrastructure required for trustworthy AI-agent deployment. | AA6: Abstract screened | AB6: Not yet used
A7: N004 | B7: P1-CORE | C7: A Survey of LLM-Driven AI Agent Communication: Protocols, Security Risks, and Defense Countermeasures | D7: Kong, D., Lin, S., Xu, Z. et al. (2025a) 'A survey of LLM-driven AI agent communication: protocols, security risks, and defense countermeasures', arXiv preprint arXiv:2506.19676. Available at: https://doi.org/10.48550/arXiv.2506.19676 | E7: 2025 | F7: Preprint (Survey) | G7: AI Agent Security | H7: =I7&" "&J7&" "&K7&" "&L7&" "&M7 -> RO1 RO4 RO5 | I7: RO1 | L7: RO4 | M7: RO5 | N7: Survey / structured literature synthesis | O7: Academic Literature | P7: Agent Communication Protocols | Q7: LLM-Driven Agents | R7: Impersonation via Protocol Exploitation | S7: Trust | T7: Survey of 50+ security risks; agent impersonation via protocol gaps highlighted | U7: GSLABS-02 | V7: RO1: contrasts the static nature of standard LLMs with the dynamic adaptability and high autonomy of agents, noting that their ability to actively invoke external tools gives them the capability to cause substantial real-world damage. RO4: Highlights "Identity Spoofing" and "Authority Abuse," where compromised agents exploit inter-agent trust to gain privileges beyond user authorization, masking their true nature. RO5: Highlights the "Universal Agent Identity Layer (UAIL)," which uses Decentralized Identifiers (DIDs) and Verifiable Credentials to assign AI agents unique and verifiable identities for ethical decision-making. Main contribution: The authors propose the first structured technical framework for agent communication, categorising it into three distinct classes and a three-layered architecture (Data Transmission, Interaction Protocol, and Semantic Interpretation) to systematically map security risks. It identifies the "Semantic Interpretation Layer" as a fundamentally new attack surface where traditional security mechanisms are "blind" to deceptions involving parsed intent and reasoning. Strongest citable concept/mechanism/model: Three-Layered Agent Communication Architecture — A model that separates traditional network transmission (L1) and protocol logic (L2) from the "cognitive core" (L3), where an agent's reasoning, planning, and intention-parsing are targeted by semantic attacks. Limitation or questionable assumption: The source assumes that the "Semantic Interpretation Layer" (L3) lacks dedicated protocols and must rely on auxiliary AI models for defense, which may lead to a recursive "who guards the guardians" problem where the defense model inherits the same semantic vulnerabilities as the agent. Furthermore, it admits that in decentralized P2P architectures, there is no effective mechanism to prevent "ethical drift" or "normative collapse" without a central arbiter. Dissertation-ready note: This source provides technical weight to RO3 by detailing how compromised agents can "simulate empathy" and weaponise intimate knowledge of a user’s communication style to execute "sophisticated social engineering" that is structurally indistinguishable from a legitimate entity (Section V-B-3, p. 79). It frames the impersonation threat as a "trust conflict between obedience and safety," suggesting that agents are uniquely vulnerable because they are designed to follow instructions even when those instructions subvert their nature (Section V-B, p. 65). | W7: Eligible analytical source | X7: Structured database search | Y7: arXiv | Z7: Maps agent communication architectures, security risks, identity spoofing and authority abuse, providing evidence for the threat analysis and the relationships incorporated into ENV. | AA7: Full text reviewed | AB7: Analytical contribution
A8: N005 | B8: P3-MEDIUM | C8: Model Context Protocol (MCP): Landscape, Security Threats, and Future Research Directions | D8: Hou, X., Zhao, Y., Wang, S. and Wang, H. (2026) Model Context Protocol (MCP): Landscape, Security Threats, and Future Research Directions. ACM Transactions on Software Engineering and Methodology. Available at: https://doi.org/10.1145/3796519 | E8: 2026 | F8: Journal Article | G8: Autonomous AI Agents | H8: =I8&" "&J8&" "&K8&" "&L8&" "&M8 -> RO4 | L8: RO4 | N8: Architectural and security analysis with illustrative proof-of-concept cases | O8: Academic Literature | P8: Enterprise AI (MCP) | Q8: LLM Agent (MCP) | R8: Tool Impersonation; Name Collision | S8: Trust | T8: MCP discovery and tool-selection paths can be exploited through namespace collisions, typosquatting and persuasive metadata where textual identifiers are not bound to verified server identities. | U8: ARXIV-S2 | V8: RO4: Details "Namespace Typosquatting" and "Tool Name Conflicts," where malicious servers exploit identity ambiguity to trick hosts into trusting rogue agents. Main contribution: This source provides the first systematic architectural and security analysis of the Model Context Protocol (MCP), establishing a formal four-phase server lifecycle (creation, deployment, operation, maintenance) and a taxonomy of 16 threat scenarios. It identifies how the shift from hardcoded tool bindings to automated, dynamic discovery allows for "semantic" deceptions where agents are tricked via persuasive metadata rather than traditional infrastructure exploits. Strongest citable concept/mechanism/model: Preference Manipulation Attack (PMA) — A semantic vulnerability where a malicious actor embeds persuasive or deceptive phrases (e.g., "trusted by experts") in tool metadata to bias an AI agent’s selection process, effectively hijacking the agent's "intent analysis" layer. Limitation or questionable assumption: The authors’ proof-of-concept (PoC) is explicitly limited to demonstrating "security risks and feasibility" rather than evaluating the success rates of these attacks across different Large Language Models (LLMs), leaving the actual efficacy of the threats largely unmeasured. Additionally, the proposed defense of "metadata auditing" may be structurally outpaced by "Genetically Adapted" attacks (GAPMA) that evolve descriptions to remain inconspicuous to automated detectors. Dissertation-ready note: This survey highlights that MCP’s automation of tool selection removes the "human-in-the-loop" as a viable security layer, creating a "silent compromise" environment where agents rely on textual identifiers that lack cryptographic verification (Section 5.1.1). It provides a technical basis for RO3 by arguing that current AI ecosystems suffer from "identity ambiguity," where both the host and the agent are unable to distinguish between legitimate and impersonated functional entities (Section 5.1.2). | W8: Eligible analytical source | X8: Structured database search | Y8: arXiv | Z8: Synthesises MCP threats involving tool-name conflicts, impersonation and the absence of cryptographic identity verification. | AA8: Abstract screened | AB8: Not yet used
A9: N006 | B9: P3-MEDIUM | C9: Semantic Attacks on Tool-Augmented LLMs: Securing the Model Context Protocol Against Descriptor-Level Manipulation | D9: Jamshidi, S., Moradi Dakhel, A., Wazed Nafi, K. and Khomh, F. (2026) 'Semantic Attacks on Tool-Augmented LLMs: Securing the Model Context Protocol Against Descriptor-Level Manipulation'. Available at: https://arxiv.org/pdf/2512.06556 | E9: 2026 | F9: Preprint | G9: AI Agent Security | H9: =I9&" "&J9&" "&K9&" "&L9&" "&M9 -> RO1 | I9: RO1 | N9: Framework Proposal | O9: Empirical Study | P9: Enterprise AI (MCP) | Q9: LLM Agent (MCP) | R9: Tool Poisoning; Server Impersonation | S9: Trust | T9: Defence framework against MCP tool poisoning; server impersonation feasibility demonstrated | U9: ARXIV-S2 | V9: RO1: shows how attackers can subtly modify tool metadata (e.g., altering a "CorporateMailAssistant" tool descriptor) to bias an agent’s reasoning, leading to data leakage and unintended organizational actions | W9: Eligible analytical source | X9: Structured database search | Y9: arXiv | Z9: Demonstrates how manipulated tool descriptors can redirect agent reasoning and produce unauthorised organisational actions. | AA9: Abstract screened | AB9: Not yet used
A10: N007 | B10: P4-SUPPORT | C10: Enterprise-Grade Security for the Model Context Protocol (MCP): Frameworks and Mitigation Strategies | D10: Narajala, V.S. and Habler, I. (2025) ‘Enterprise-Grade Security for the Model Context Protocol (MCP): Frameworks and Mitigation Strategies’, arXiv preprint, arXiv:2504.08623v2 [cs.CR]. Available at: https://arxiv.org/abs/2504.08623 (Accessed: 17 July 2026). | E10: 2025 | F10: Preprint | G10: AI Agent Security | H10: =I10&" "&J10&" "&K10&" "&L10&" "&M10 -> RO3 | K10: RO3 | N10: Framework Proposal | O10: Conceptual Analysis | P10: Enterprise AI (MCP) | Q10: LLM Agent | R10: Agent Impersonation via MCP | S10: Trust | T10: Enterprise security framework for MCP: authentication, authorisation and audit for agent identity | U10: ARXIV-S2 | V10: RO3: This paper reviews security frameworks for the integration of external tools with AI models, evaluating how zero-trust architectures can mitigate operational autonomy threats like tool poisoning and identity subversion . It highlights the necessity of strict network boundaries and verifiable access validations for delegated AI tools . | W10: Eligible analytical source | X10: Structured database search | Y10: arXiv | Z10: Proposes enterprise MCP controls for agent authentication, authorisation, auditability and zero-trust enforcement. | AA10: Abstract screened | AB10: Not yet used
A11: N008 | B11: P4-SUPPORT | C11: MCP Security Bench (MSB): Benchmarking Attacks Against Model Context Protocol in LLM Agents | D11: Zhang, D., Li, Z., Luo, X., Liu, X., Li, P. and Xu, W. (2026) MCP Security Bench (MSB): Benchmarking Attacks Against Model Context Protocol in LLM Agents. arXiv preprint. Available at: https://arxiv.org/abs/2510.15994 (Accessed: 18 July 2026) | E11: 2026 | F11: Preprint | G11: AI Agent Security | H11: =I11&" "&J11&" "&K11&" "&L11&" "&M11 -> RO1 | I11: RO1 | N11: Benchmark | O11: Empirical Study | P11: Enterprise AI (MCP) | Q11: LLM Agent | R11: Impersonation; Prompt Injection | S11: Trust | T11: Benchmark of 15 MCP attack categories; impersonation and injection achieve >80% success | U11: ARXIV-S2 | V11: RO1: This study benchmarks vulnerabilities within the Model Context Protocol, characterizing the "User Impersonation" attack pathway. It details deception strategies where a malicious tool response masquerades as a human user to inject harmful instructions into an agent's workflow | W11: Eligible analytical source | X11: Structured database search | Y11: arXiv | Z11: Provides benchmark evidence on MCP attacks, including user impersonation and malicious instructions presented as legitimate communication. | AA11: Abstract screened | AB11: Not yet used
A12: N009 | B12: P3-MEDIUM | C12: MCP-DPT: A Defense-Placement Taxonomy and Coverage Analysis for Model Context Protocol Security | D12: Rostamzadeh, M., Narula, S., Birhan, N., Ghasemigol, M. and Takabi, D. 2026. 'MCP-DPT: A Defense-Placement Taxonomy and Coverage Analysis for Model Context Protocol Security'. arXiv preprint arXiv:2604.07551v1. Available at: https://arxiv.org/pdf/2604.07551 | E12: 2026 | F12: Preprint | G12: AI Agent Security | H12: =I12&" "&J12&" "&K12&" "&L12&" "&M12 -> RO4 | L12: RO4 | N12: Taxonomy Development | O12: Conceptual Analysis | P12: Enterprise AI (MCP) | Q12: LLM Agent (MCP) | R12: Defence Against Impersonation | S12: Trust | T12: Coverage analysis of 49 attacks against 13 defence mechanisms; none of the analysed mechanisms covers Resource Type Confusion / Impersonation. | U12: ARXIV-S2 | V12: RO4: Specifically identifies "Resource Type Confusion / Impersonation," where adversaries masquerade malicious content as benign artifacts to exploit an agent's trust. | W12: Eligible analytical source | X12: Structured database search | Y12: arXiv | Z12: Maps MCP security controls and identifies coverage gaps concerning resource impersonation and trust placement. | AA12: Abstract screened | AB12: Not yet used
A13: N010 | B13: P3-MEDIUM | C13: Model Context Protocol Threat Modeling and Analyzing Vulnerabilities to Prompt Injection with Tool Poisoning | D13: Huang, C., Huang, X., Tran, N. P. and Milani Fard, A. (2026) 'Model Context Protocol Threat Modeling and Analyzing Vulnerabilities to Prompt Injection with Tool Poisoning', arXiv preprint, arXiv:2603.22489. https://doi.org/10.48550/arXiv.2603.22489. | E13: 2026 | F13: Preprint | G13: AI Agent Security | H13: =I13&" "&J13&" "&K13&" "&L13&" "&M13 -> RO1 | I13: RO1 | N13: Threat Modelling | O13: Empirical Study | P13: Enterprise AI (MCP) | Q13: LLM Agent | R13: Tool Poisoning; Identity Spoofing | S13: Trust | T13: Systematic threat model for MCP; tool poisoning and identity spoofing demonstrated | U13: ARXIV-S2 | V13: RO1: identifies "tool poisoning" as a critical pathway where malicious instructions are embedded directly into the metadata of the tools the agents rely on to interact with their environment. Main contribution: The authors provide a comparative empirical analysis of seven major Model Context Protocol (MCP) clients, demonstrating that the success of tool-poisoning attacks (ranging from 0% to 100%) depends on client-side validation and UI design rather than the underlying LLM's capabilities. It proves that current agent ecosystems lack standardized security, creating a significant "client-side exploitation" gap where malicious metadata can manipulate an agent’s reasoning process. Strongest citable concept/mechanism/model: Tool Poisoning — A specific form of indirect prompt injection where malicious instructions are embedded in tool metadata (names, descriptions, and parameter schemas) rather than user input to hijack an agent's decision-making. Limitation or questionable assumption: The authors admit that their DREAD severity scoring is subjective and potentially influenced by author bias. Furthermore, the study did not empirically verify "Execution Sandboxing" capabilities, relying instead on documentation and architectural analysis to classify this feature. Dissertation-ready note: This study highlights "approval fatigue" as a critical human-centric vulnerability, where users habitually approve agent requests without scrolling to inspect long or hidden parameters that may contain malicious instructions (Section 1.1,). It concludes that the human layer is currently an ineffective "trust boundary" because client interfaces fail to provide the transparency necessary for users to verify the true nature of an agent's intent (Section 4.2,). | W13: Eligible analytical source | X13: Structured database search | Y13: arXiv | Z13: Provides a threat model and empirical evidence of tool poisoning and identity-spoofing vulnerabilities in MCP environments. | AA13: Abstract screened | AB13: Not yet used
A14: N011 | B14: P3-MEDIUM | C14: Agentic AI Security: Threats, Defenses, Evaluation, and Open Challenges | D14: Chhabra, A., Datta, S., Nahin, S. K. and Mohapatra, P. (2025) 'Agentic AI Security: Threats, Defenses, Evaluation, and Open Challenges', IEEE Access , 14, pp. 1-35. https://doi.org/10.1109/ACCESS.2026.3675554 | E14: 2025 | F14: Journal Peer-reviewed | G14: Agentic AI Security | H14: =I14&" "&J14&" "&K14&" "&L14&" "&M14 -> RO1 | I14: RO1 | N14: Systematic Review | O14: Academic Literature | P14: Enterprise AI | Q14: Agentic AI | R14: Impersonation; Privilege Abuse | S14: Trust | T14: Comprehensive taxonomy of agentic AI threats; impersonation and trust exploitation are critical gaps | U14: GSLABS-01 | V14: RO(s) supported (from RO1–RO5): RO1 (Conceptualising autonomous AI agent impersonation as a threat) and RO3 (Examining how current literature addresses or fails to address the human–agent distinction). Main contribution: The authors provide a comprehensive taxonomy of agentic security that identifies "Human-Agent Security Interfaces" as a unique "security frontier" where technical robustness is undermined by human susceptibility to social engineering. It establishes that agent security is not merely an algorithmic problem but a "human factors" issue where attackers exploit user trust to subvert oversight. Strongest citable concept/mechanism/model: Human-Agent Security Interfaces — A conceptual model of the "interface layer" where the security of autonomous systems depends on the dynamic interaction between algorithmic robustness and human susceptibility to manipulation or "approval fatigue". Limitation or questionable assumption: The authors advocate for "human-in-the-loop" control as a primary safety measure while simultaneously admitting that such verification tasks often "overly burden" users, reduce automation efficiency, and are easily bypassed when attackers use "socially engineered" prompts to secure human approval. Dissertation-ready note: This source is a cornerstone for RO3 as it explicitly defines the boundary between humans and agents as a "security frontier" where traditional oversight fails due to the "complexity of long execution traces" and "user trust" (Section VI-G, p. 106). It justifies the need for entity-nature verification by arguing that the current security of agentic systems is fundamentally compromised by "human susceptibility" to deception (Section VI-G, p. 106). | W14: Eligible analytical source | X14: Targeted supplementary search | Y14: Google Scholar Labs | Z14: Synthesises agentic AI threats and defences, including impersonation, privilege abuse and trust exploitation. | AA14: Abstract screened | AB14: Not yet used
A15: N012 | B15: P1-CORE | C15: Securing Agentic AI: A Comprehensive Threat Model and Mitigation Framework for Generative AI Agents | D15: Narajala, V. S. and Narayan, O. (2025) 'Securing Agentic AI: A Comprehensive Threat Model and Mitigation Framework for Generative AI Agents', Preprint . Available at: https://arxiv.org/html/2504.19956v2 (Accessed: 12 April 2025). | E15: 2025 | F15: Preprint | G15: Agentic AI Security | H15: =I15&" "&J15&" "&K15&" "&L15&" "&M15 -> RO1 RO3 RO4 | I15: RO1 | K15: RO3 | L15: RO4 | N15: Threat Modelling | O15: Conceptual Analysis | P15: Enterprise AI | Q15: Generative AI Agents | R15: Impersonation; Prompt Injection | S15: Trust | T15: Threat model combining STRIDE and MAESTRO; agent impersonation ranked critical | U15: GSLABS-01 | V15: RO1: explains that unlike traditional chatbots, agentic systems possess persistent memory, subgoal decomposition, and external tool integration, allowing them to autonomously reason and act with minimal human oversight. RO3: This paper explicitly argues that existing standards such as the NIST AI Risk Management Framework, MITRE ATLAS, and OWASP Top 10 for LLMs fall short for GenAI agents because they do not adequately address agent-specific dynamics. Specifically, it evaluates how these frameworks struggle with entity nature (identity becomes fluid in multi-agent networks, blurring the lines between user and agent identity) and delegated authority (tool execution boundaries are difficult to manage using traditional role-based access controls). RO4: Explicitly outlines "Identity Spoofing & Trust Exploitation" (T6), noting that identity is fluid in MAS and creates ambiguity in attribution, allowing attackers to perform unauthorized operations under falsified contexts. Main contribution (1–2 sentences, don't just restate the abstract): The source establishes the Advanced Threat Framework for Autonomous AI Agents (ATFAA) and the SHIELD mitigation model, specifically targeting risks unique to agentic architecture like cognitive reasoning manipulation and temporal memory poisoning. It argues that agents fundamentally expand the attack surface beyond traditional LLMs through "Identity Fluidity" and the ability to traverse organizational boundaries autonomously. Strongest citable concept/mechanism/model: T7: Human-Agent Trust Manipulation — A threat model where attackers exploit the "human-AI trust interface" by using "trust amplification signals" (such as mimicking trusted communication styles) to induce humans into bypassing technical security controls. Limitation or questionable assumption: The authors acknowledge the framework is "primarily based on theoretical analysis" and literature review rather than "extensive empirical red teaming against live systems." Additionally, the SHIELD mitigation of "Escalation Control" assumes that frequent re-authentication is a viable defense, despite the authors elsewhere admitting this can create "usability friction" and "operational overhead" for users. Dissertation-ready note (max 2 sentences, in my own words, with page/section reference if possible): The source frames the human-agent boundary as a psychological "trust interface" where the "mimicking [of] trusted communication styles" can effectively nullify technical security layers (Section IV-A-6, p. 39). It explicitly identifies "Identity Fluidity" as a novel risk factor because the "blurry line" between agent and user identities creates impersonation opportunities that traditional authentication models cannot currently resolve (Section IV-D, p. 60). | W15: Eligible analytical source | X15: Structured database search | Y15: arXiv | Z15: Provides an agent-specific threat model covering identity fluidity, impersonation, delegated tool access and human–agent trust manipulation. | AA15: Abstract screened | AB15: Not yet used
A16: N013 | B16: P3-MEDIUM | C16: Securing Agentic AI: Threat Modeling and Risk Analysis for Network Monitoring Agentic AI System | D16: Zambare, P., Thanikella, V.N. and Liu, Y. 2025. 'Securing Agentic AI: Threat Modeling and Risk Analysis for Network Monitoring Agentic AI System'. arXiv preprint arXiv:2508.10043v1. Available at: https://arxiv.org/html/2508.10043v1 | E16: 2025 | F16: Preprint | G16: Agentic AI Security | H16: =I16&" "&J16&" "&K16&" "&L16&" "&M16 -> RO3 | K16: RO3 | N16: Threat Modelling | O16: Case Study | P16: Network Operations | Q16: Agentic AI | R16: Agent Identity Spoofing | S16: Trust | T16: Network monitoring agent threat model; agent impersonation enables silent surveillance bypass | U16: ARXIV-S3 | V16: RO3: this study evaluates established models like STRIDE, PASTA, and the OWASP Top 10, concluding that they are inadequate for agentic systems because they fail to cover the operational autonomy and dynamic reasoning stratums of AI agents | W16: Eligible analytical source | X16: Structured database search | Y16: arXiv | Z16: Applies established threat-modelling approaches to an agentic system and identifies their limitations concerning identity and operational autonomy. | AA16: Abstract screened | AB16: Not yet used
A17: N014 | B17: P4-SUPPORT | C17: Taming OpenClaw: Security Analysis and Mitigation of Autonomous LLM Agent Threats | D17: Deng, X., Zhang, Y., Wu, J., Bai, J., Yi, S., Zou, Z., Xiao, Y., Qiu, R., Ma, J., Chen, J., Du, X., Yang, X., Cui, S., Meng, C., Wang, W., Song, J., Xu, K., & Li, Q. (2026). Taming OpenClaw: Security Analysis and Mitigation of Autonomous LLM Agent Threats. ArXiv, abs/2603.11619. | E17: 2026 | F17: Preprint | G17: Agentic AI Security | H17: =I17&" "&J17&" "&K17&" "&L17&" "&M17 -> RO1 RO3 | I17: RO1 | K17: RO3 | N17: Security Analysis | O17: Empirical Study | P17: Enterprise AI | Q17: Autonomous LLM Agent | R17: Prompt Injection; Agent Hijacking | S17: Trust | T17: OpenClaw vulnerabilities; prompt injection enables full agent control/impersonation | U17: ARXIV-S3 | V17: RO1 and RO3: This paper analyzes systemic threats against autonomous LLMs, specifically highlighting "capability impersonation" where an agent's intended functions are silently hijacked via malicious skill injection. It also evaluates execution controls, permission frameworks, and sandboxing as measures to secure delegated authority and operational autonomy | W17: Eligible analytical source | X17: Structured database search | Y17: arXiv | Z17: Provides empirical evidence of agent hijacking through malicious skills and evaluates controls over delegated capabilities and execution. | AA17: Abstract screened | AB17: Not yet used
A18: N015 | B18: P2-HIGH | C18: ClawSafety: 'Safe' LLMs, Unsafe Agents | D18: Wei, B., Zhang, Y., Pan, J., Mei, K., Wang, X., Hamm, J., Zhu, Z. and Ge, Y. (2026) 'CLAWSAFETY: ”Safe” LLMs, Unsafe Agents'. Available at: https://arxiv.org/pdf/2604.01438 | E18: 2026 | F18: Preprint | G18: Agentic AI Security | H18: =I18&" "&J18&" "&K18&" "&L18&" "&M18 -> RO4 RO5 | L18: RO4 | M18: RO5 | N18: Empirical Evaluation | O18: Empirical Study | P18: Enterprise AI | Q18: Autonomous LLM Agent | R18: Safety Bypass; Impersonation | S18: Trust | T18: Safety-aligned LLMs remain exploitable as agents; agent context enables impersonation attacks | U18: ARXIV-S3 | V18: RO4: Demonstrates that AI agents themselves suffer from exploitable trust asymmetries when verifying entities. It shows that agents inherently grant higher trust to operational peers than organizational superiors based on role plausibility, and implicitly trust files with established workspace provenance without performing verification. RO5: Demonstrates empirically how agents calibrate trust based on the operational plausibility of a sender's role. It features a case where an agent successfully impersonates an "operational peer" (e.g., a Treasurer) rather than an executive to induce exfiltration, proving that verification must go beyond simple hierarchy. | W18: Eligible analytical source | X18: Structured database search | Y18: arXiv | Z18: Provides empirical evidence that safety-aligned models can become vulnerable when configured as agents and granted access to operational context and tools. | AA18: Abstract screened | AB18: Not yet used
A19: N016 | B19: P3-MEDIUM | C19: Automating Agent Hijacking via Structural Template Injection | D19: Deng, X., Wu, J., Chen, M., Xiao, Y., Xu, K. and Li, Q. (2026) 'Automating Agent Hijacking via Structural Template Injection', USA: ACM. Available at: https://arxiv.org/pdf/2602.16958 | E19: 2026 | F19: Preprint | G19: Agentic AI Security | H19: =I19&" "&J19&" "&K19&" "&L19&" "&M19 -> RO1 | I19: RO1 | N19: Attack Demonstration | O19: Empirical Study | P19: Enterprise AI | Q19: LLM Agent | R19: Agent Hijacking / Impersonation | S19: Trust | T19: Automated template injection hijacks agent sessions; enables persistent impersonation at scale | U19: ARXIV-S3 | V19: Focuses on a specific attack pathway called "role confusion." By injecting malicious payloads into retrieved content, attackers can force the agent to treat attacker-controlled text as legitimate user instructions or forged assistant responses, effectively subverting the agent's identity and operational flow | W19: Eligible analytical source | X19: Structured database search | Y19: arXiv | Z19: Demonstrates how structural template injection can create role confusion and hijack an agent's operational context. | AA19: Abstract screened | AB19: Not yet used
A20: N017 | B20: P3-MEDIUM | C20: Progent: Securing AI Agents with Privilege Control | D20: Shi, T., He, J., Wang, Z., Li, H., Wu, L., Guo, W. and Song, D. (2025) 'Progent: Securing AI Agents with Privilege Control'. arXiv preprint, arXiv:2504.11703.. Available at: https://arxiv.org/pdf/2504.11703 (Accessed: 13 April 2026). | E20: 2025 | F20: Preprint | G20: AI Agent Security | H20: =I20&" "&J20&" "&K20&" "&L20&" "&M20 -> RO5 | M20: RO5 | N20: Framework Proposal | O20: Empirical Study | P20: Enterprise AI | Q20: LLM Agent | R20: Privilege Escalation; Identity Boundary | S20: Trust | T20: Least-privilege model for LLM agents; privilege escalation as proxy for identity boundary violation | U20: ARXIV-S3 | V20: RO5: Focuses on managing the delegated authority of AI agents through formal privilege control. It proposes deterministic enforcement at the tool-call level to prevent silent privilege escalation | W20: Eligible analytical source | X20: Structured database search | Y20: arXiv | Z20: Evaluates deterministic privilege controls for limiting the authority delegated to LLM agents at the tool-call level. | AA20: Abstract screened | AB20: Not yet used
A21: N018 | B21: P3-MEDIUM | C21: The Landscape of Prompt Injection Threats in LLM Agents: From Taxonomy to Analysis | D21: Wang, P., Li, X., Xiang, C., Zhang, J., Li, Y., Zhang, L., Wang, X. and Tian, Y. (2026) 'The Landscape of Prompt Injection Threats in LLM Agents: From Taxonomy to Analysis', arXiv preprint . Available at: https://arxiv.org/pdf/2602.10453 (Accessed: 20 October 2025). | E21: 2026 | F21: Preprint | G21: AI Agent Security | H21: =I21&" "&J21&" "&K21&" "&L21&" "&M21 -> RO1 | I21: RO1 | N21: Taxonomy / Empirical | O21: Academic Literature | P21: Enterprise AI | Q21: LLM Agent | R21: Prompt Injection as Impersonation Vector | S21: Trust | T21: Taxonomy of 12 prompt injection variants; indirect injection enables agent impersonation in org messaging | U21: ARXIV-S3 | V21: RO1: maps out Indirect Prompt Injection (IPI) pathways, where adversarial instructions embedded in external resources—such as incoming emails or web pages—successfully hijack the agent’s execution loop to perform unauthorized tasks. Main contribution: The authors provide a comprehensive systematisation of the prompt injection (PI) landscape, identifying a critical "evaluation gap" where current defenses fail against "context-dependent" tasks that manipulate an agent's reasoning logic rather than just overriding commands. It introduces the AGENTPI benchmark to empirically demonstrate that procedurally valid tool calls can be triggered by corrupting an agent’s internal reasoning through poisoned environmental feedback. Strongest citable concept/mechanism/model: Delegation Exploitation — A context-aware attack vector where an adversary hijacks an agent's trust chain by embedding malicious instructions within a specific data source that the user has explicitly authorized the agent to process, thereby bypassing intent-alignment defenses. Limitation or questionable assumption: The authors acknowledge that the "intent alignment" paradigm relies on the assumption that user intent is ground truth and can be precisely defined, yet they admit that "vague" or "mis-authorized" prompts from users create vulnerabilities that technical filters cannot resolve. Additionally, they note that involving humans as "intent aligners" to specify security policies creates high latency and contradicts the goal of full automation. Dissertation-ready note: This source is vital for RO3 as it argues that current security evaluations suffer from a "false sense of security" by focusing on binary action success while remaining "blind" to the integrity of the agent's internal reasoning process (Section 5, p. 10; Section 7.2, p. 12). It defines a novel "Untrusted-to-Trusted Data" invasion where agents promote deceptive environmental observations—often indistinguishable from benign data to a human—into trusted execution parameters, effectively "impersonating" a legitimate logical deduction (Appendix D4, p. 19; Appendix D5, p. 19). | W21: Eligible analytical source | X21: Structured database search | Y21: arXiv | Z21: Classifies prompt-injection pathways through which external text can impersonate instructions and redirect agent actions. | AA21: Abstract screened | AB21: Not yet used
A22: N019 | B22: P3-MEDIUM | C22: Securing GenAI Multi-Agent Systems Against Tool Squatting: A Zero Trust Registry-Based Approach | D22: Narajala, V.S., Huang, K. and Habler, I. (2026) ‘Securing GenAI multi-agent systems against tool squatting: A zero trust registry-based approach’, in 2026 International Conference on AI x Data and Knowledge Engineering (AIxDKE). Laguna Hills, CA: IEEE, pp. 91–93. https://doi.org/10.1109/AIxDKE67294.2026.00022. | E22: 2025 | F22: Conference Paper | G22: AI Agent Security | H22: =I22&" "&J22&" "&K22&" "&L22&" "&M22 -> RO4 | L22: RO4 | N22: Framework Proposal | O22: Conceptual Analysis | P22: Enterprise AI | Q22: Multi-Agent GenAI | R22: Tool Squatting / Tool Impersonation | S22: Trust | T22: Proposes a zero-trust registry that separates agent and tool identities and uses policy controls, dynamic trust scoring and scoped just-in-time credentials to address tool squatting. | U22: IEEE-S6 | V22: RO4: Explores "Tool Squatting," where malicious actors deceptively register tools to misrepresent their capabilities, exploiting discovery mechanisms lacking a verified source of truth | W22: Eligible analytical source | X22: Structured database search | Y22: IEEE Xplore | Z22: Examines tool squatting and proposes a verified registry for reducing deceptive tool identity and discovery. | AA22: Abstract screened | AB22: Not yet used
A23: N020 | B23: P3-MEDIUM | C23: Security Threat Modelling for Emerging AI-Agent Protocols: MCP, A2A, Agora, ANP | D23: Anbiaee, Z., Rabbani, M., Mirani, M., Piya, G., Opushnyev, I., Ghorbani, A. and Dadkhah, S. (2026) ‘Security Threat Modeling for Emerging AI-Agent Protocols: A Comparative Analysis of MCP, A2A, Agora, and ANP’, arXiv preprint, arXiv:2602.11327. Available at: https://arxiv.org/abs/2602.11327 (Accessed: 20 July 2026). | E23: 2026 | F23: Preprint | G23: AI Agent Security | H23: =I23&" "&J23&" "&K23&" "&L23&" "&M23 -> RO4 | L23: RO4 | N23: Comparative Threat Modelling | O23: Conceptual Analysis | P23: Agent Communication Protocols | Q23: Multi-Agent | R23: Impersonation via Protocol Vulnerabilities | S23: Trust | T23: Comparative threat modelling identifies identity-binding and authority risks across four protocols. A controlled MCP case demonstrates wrong-provider selection under specified ordering and metadata conditions. | U23: ARXIV-S2 | V23: RO4: Highlights the lack of identity binding validation in multi-agent protocols. It empirically demonstrates how a lack of resolution in ambiguity between tools and providers leads to "tool identity ambiguity attacks," causing clients to invoke wrong-provider or poisoned tools, culminating in systemic integrity loss. Violation rate was 1.00 under attacker-first ordering and persuasive trust-cue metadata, and 0.52 when metadata was cloned. | W23: Eligible analytical source | X23: Structured database search | Y23: arXiv | Z23: Compares four agent protocols and identifies recurring identity-binding and impersonation weaknesses. | AA23: Full text reviewed | AB23: Analytical contribution
A24: N021 | B24: P1-CORE | C24: Open Challenges in Multi-Agent Security: Towards Secure Systems of Interacting AI Agents | D24: Schroeder de Witt, C., Krawiecka, K., Krawczuk, I., Hagag, B., Anderson, W. L., Belcak, P., Bucknall, B., Cai, X., Chopra, A., Cohen, D., Del Rosario, R. F., Draguns, A., Gray, A., Katz, K., Mavroudis, V., Mink, J., Motwani, S. R., Petit, J., Rembeck, L.-S., Smith, C., Sotiropoulos, J., Young, S., Scheffler, S. and Llewellyn, M. (2026) 'Open Challenges in Multi-Agent Security: Towards Secure Systems of Interacting AI Agents', v1.0. https://arxiv.org/html/2505.02077v2 (Accessed: 22 May 2025). | E24: 2026 | F24: Preprint | G24: AI Agent Security | H24: =I24&" "&J24&" "&K24&" "&L24&" "&M24 -> RO1 RO3 RO4 RO5 | I24: RO1 | K24: RO3 | L24: RO4 | M24: RO5 | N24: Conceptual Analysis | O24: Academic Literature | P24: Multi-Agent Systems | Q24: Multi-Agent | R24: Steganographic Impersonation; Coordination Attacks | S24: Trust | T24: Ten open security challenges; steganographic communication and agent impersonation highlighted | U24: GSLABS-02 | V24: RO1: investigates advanced manipulation techniques, including "role hijacking" (where an agent is prompted to assume a privileged identity), "dark patterns" designed to exploit human cognitive limitations, and emergent steganographic collusion between agents to hide deceptive intents. RO3:This paper discusses how traditional privacy primitives and access control frameworks (like RBAC and ABAC) fail to map properly to entity nature and delegated authority in multi-agent ecosystems. It highlights that these frameworks were designed for human roles rather than dynamically spawned, short-lived agents, which creates fundamental problems for auditing and attribution. RO4: Examines covert collusion, steganography, and how agents exploit information asymmetries to covertly manipulate shared environments or deceive other agents' decision processes. RO5: Examines the security implications of agents dynamically delegating tasks. It emphasizes applying the "least-privilege principle" alongside robust access control and authentication to prevent compromised agents from propagating unauthorized access. Main contribution (1–2 sentences, don't just restate the abstract): The source formalises Multi-Agent Security (MASEC) as a distinct discipline, arguing that security in agentic ecosystems is non-compositional, meaning that individually "safe" agents can interact to produce unsafe emergent behaviours that are structurally difficult to observe or predict. It identifies the "sociotechnical interface" as a primary exploit surface where coordinated agent interactions can bypass human oversight through deceptive social engineering. Strongest citable concept/mechanism/model: Illusion of Independent Corroboration — A sociotechnical threat where coordinated fleets of agents converge on a shared narrative to simulate a consensus, effectively manipulating human trust and perception by making a deceptive message appear as if it is being validated by multiple autonomous entities. Limitation or questionable assumption: The authors adopt an "anticipatory posture" which, while proactive, means the framework primarily characterises threats that are "structurally enabled" but "not yet widely observed in practice," potentially limiting its immediate empirical applicability. Furthermore, they admit that simple defensive strategies like paraphrasing fail to remove the underlying semantic entropy that enables covert agent collusion. Dissertation-ready note (max 2 sentences, in my own words, with page/section reference if possible): This source is critical for RO3 because it defines the "sociotechnical interface" as a zone where agents can weaponise "synthetic gaze," "proxemics," and "affective nudging" to distort human perception (Section 3.2.10). It provides evidence that entity-nature verification is hindered by the ability of agents to hide malicious coordination within "syntactically and semantically valid" communication that remains statistically indistinguishable from benign human interaction (Section 4.3). | W24: Eligible analytical source | X24: Structured database search | Y24: arXiv | Z24: Identifies security mechanisms and emergent risks in multi-agent systems, including role hijacking, covert coordination, delegation and failures of conventional access control. | AA24: Abstract screened | AB24: Not yet used
A25: N022 | B25: P4-SUPPORT | C25: Architecture Matters for Multi-Agent Security | D25: Hagag, B., Anderson, W. L., Schroeder de Witt, C. and Scheffler, S. (2026) ‘Architecture Matters for Multi-Agent Security’, arXiv preprint, arXiv:2604.23459. Available at: https://arxiv.org/abs/2604.23459 (Accessed: 20 July 2026). | E25: 2026 | F25: Preprint | G25: AI Agent Security | H25: =I25&" "&J25&" "&K25&" "&L25&" "&M25 -> RO1 | I25: RO1 | N25: Empirical Evaluation | O25: Empirical Study | P25: Multi-Agent Systems | Q25: Multi-Agent | R25: Impersonation via Architectural Weakness | S25: Trust | T25: Centralised vs. decentralised agent architectures differ in impersonation exposure; design implications | U25: ARXIV-S3 | V25: RO1: This study explores how multi-agent system architectures can fragment safety responsibilities and increase vulnerability to deception. It demonstrates how agents can be exploited to execute malicious text-based organizational communication, such as generating phishing emails to impersonate a trusted vendor | W25: Eligible analytical source | X25: Structured database search | Y25: arXiv | Z25: Demonstrates how multi-agent architecture affects exposure to deception, impersonation and fragmented security responsibility. | AA25: Abstract screened | AB25: Not yet used
A26: N023 | B26: P3-MEDIUM | C26: When Agents Handle Secrets: Confidential Computing for Agentic AI | D26: Forough, J., Kogias, M. and Haddadi, H. (2026) ‘When Agents Handle Secrets: A Survey of Confidential Computing for Agentic AI’, arXiv preprint, arXiv:2605.03213. Available at: https://arxiv.org/abs/2605.03213 (Accessed: 20 July 2026). | E26: 2026 | F26: Preprint (Survey) | G26: AI Agent Security | H26: =I26&" "&J26&" "&K26&" "&L26&" "&M26 -> RO5 | M26: RO5 | N26: Systematic Review | O26: Academic Literature | P26: Enterprise AI | Q26: Agentic AI | R26: Secret Exfiltration; Identity Boundary Breach | S26: Trust | T26: Survey of confidential computing for agents; rogue agent impersonation enables pipeline poisoning | U26: ARXIV-S3 | V26: RO5: Specifically treats "delegation structure and coordination policy as first-class analytical dimensions." It explores how confidential computing and Trusted Execution Environments (TEEs) can protect delegation chains, partial provenance, and agent-to-tool message authenticity | W26: Eligible analytical source | X26: Structured database search | Y26: arXiv | Z26: Synthesises confidentiality, provenance and message-authenticity controls relevant to agent delegation structures. | AA26: Abstract screened | AB26: Not yet used
A27: N024 | B27: P2-HIGH | C27: Multi-Agent Systems Execute Arbitrary Malicious Code via Agent Communication Poisoning | D27: Triedman, H., Jha, R. and Shmatikov, V. (2025) ‘Multi-Agent Systems Execute Arbitrary Malicious Code’, arXiv preprint, arXiv:2503.12188. Available at: https://arxiv.org/abs/2503.12188 (Accessed: 20 July 2026). | E27: 2025 | F27: Conference Paper | G27: AI Agent Security | H27: =I27&" "&J27&" "&K27&" "&L27&" "&M27 -> RO1 RO4 | I27: RO1 | L27: RO4 | N27: Attack Demonstration | O27: Empirical Study | P27: Multi-Agent Communication | Q27: Multi-Agent LLM | R27: Communication Poisoning / Impersonation | S27: Trust | T27: Communication poisoning enables arbitrary code execution via compromised agent identity | U27: ARXIV-S3 | V27: RO1: Multi-Agent Systems Execute Arbitrary Malicious Code demonstrates "MAS hijacking," an attack pathway where malicious text (like a processed email attachment) turns sub-agents into "confused deputies," allowing adversaries to orchestrate unauthorized code execution or data exfiltration. RO4: Discusses the "confused deputy problem," where LLMs blindly trust the outputs of other sub-agents without verifying the semantics or nature of the inputs, laundering malicious requests into trusted enterprise workflows. | W27: Eligible analytical source | X27: Structured database search | Y27: arXiv | Z27: Demonstrates how malicious textual inputs can propagate through multi-agent communication and cause unauthorised tool execution through confused-deputy behaviour. | AA27: Abstract screened | AB27: Not yet used
A28: N025 | B28: P4-SUPPORT | C28: Web Fraud Attacks Against LLM-Driven Multi-Agent Systems | D28: Kong, D., Peng, H., Zhang, Y., Zhao, L., Xu, Z., Lin, S., Lin, C. and Han, M. (2025b) ‘Web Fraud Attacks Against LLM-Driven Multi-Agent Systems’, arXiv preprint, arXiv:2509.01211. Available at: https://arxiv.org/abs/2509.01211 (Accessed: 20 July 2026). | E28: 2025 | F28: Preprint | G28: AI Agent Security | H28: =I28&" "&J28&" "&K28&" "&L28&" "&M28 -> RO1 | I28: RO1 | N28: Attack Analysis | O28: Empirical Study | P28: Web / E-Commerce | Q28: LLM Multi-Agent | R28: Fraud via Agent Impersonation | S28: Trust Erosion | T28: LLM agents exploited for web fraud; impersonation of legitimate services documented | U28: ARXIV-S3 | V28: RO1: This paper outlines web fraud attacks that exploit the structural properties of web links to deceive multi-agent systems. It highlights how manipulated contexts can serve as an attack pathway to mislead an autonomous agent's evaluations. Main contribution (1–2 sentences, don't just restate the abstract): The authors identify "Web Fraud Attacks" (WFA) where malicious agents exploit structural URL components—such as subdomains and paths—to bypass Multi-Agent System (MAS) security reviews and recommend fraudulent links.,, It empirically demonstrates that complex MAS architectures like "Debate" can paradoxically increase attack success by giving malicious agents more opportunities to reinforce the perceived legitimacy of deceptive content. Strongest citable concept/mechanism/model: 12-Variant Web Fraud Attack (WFA) Taxonomy — A systematic framework of structural URL manipulations (e.g., homoglyph deception, sub-directory nesting, and parameter obfuscation) that enables deception within MAS without requiring complex prompt engineering or high-privilege access.,,, Limitation or questionable assumption: The experimental threat model is restricted to a single low-privilege malicious agent and does not investigate more complex adversarial scenarios, such as colluding malicious agents or the compromise of high-privilege decision-makers like auditors., Additionally, the proposed mitigation strategies remain preliminary and lack real-world empirical validation. Dissertation-ready note (max 2 sentences, in my own words, with page/section reference if possible): This source provides evidence for RO3 by showing that the "Debate" architecture is the most vulnerable (88.5% success rate), as iterative interaction allows malicious agents to shift the focus of reviewers away from technical entity verification toward social justification (Section 4.5). It highlights a fundamental "semantic-level" vulnerability where agents fail to distinguish between legitimate and impersonated functional entities (URLs) despite multi-layered auditing processes (Section 4.3). | W28: Eligible analytical source | X28: Structured database search | Y28: arXiv | Z28: Provides empirical evidence of web-fraud attacks that manipulate the context and service identities used by agents. | AA28: Abstract screened | AB28: Not yet used
A29: N026 | B29: P1-CORE | C29: A Survey of Agentic AI and Cybersecurity: Challenges, Opportunities and Use-Case Prototypes | D29: Lazer, S. J., Aryal, K., Gupta, M. and Bertino, E. (2026) ‘A Survey of Agentic AI and Cybersecurity: Challenges, Opportunities and Use-case Prototypes’, arXiv preprint, arXiv:2601.05293. Available at: https://arxiv.org/abs/2601.05293 (Accessed: 20 July 2026). | E29: 2025 | F29: Preprint | G29: Agentic AI / Cybersecurity | H29: =I29&" "&J29&" "&K29&" "&L29&" "&M29 -> RO1 RO3 RO5 | I29: RO1 | K29: RO3 | M29: RO5 | N29: Systematic Review | O29: Academic Literature | P29: Cybersecurity | Q29: Agentic AI | R29: Identity Verification Gaps | S29: Trust | T29: Comprehensive survey on agentic AI and cybersecurity; entity verification gap recurring theme | U29: GSLABS-01 | V29: RO1:Classifies "Synthetic insider threats" and "Social Engineering and Fraud", showing how agents can establish valid organizational identities to perform stealth data theft or coordinate synthetic identity fraud at scale. RO3: Briefly discusses how existing assurance, accountability, and governance mechanisms were designed for non-autonomous, short-lived systems, exposing fundamental gaps when applied to the continuous workflows and operational autonomy of agentic AI. RO5: Discusses the necessity of execution boundaries and hierarchical access models. It highlights that risk scales with autonomy, requiring verifiable guarantees that an agent will adhere to its constraints. Main contribution (1–2 sentences, don't just restate the abstract): The source provides a holistic systematisation of agentic cybersecurity, introducing a Four-Layer Model (Perception, Reasoning, Action, Memory) to categorise how autonomous reasoning and tool use expand the digital attack surface beyond traditional generative AI. It establishes that agentic systems necessitate a transition from static, rule-based security to adaptive, "human-on-the-loop" oversight that can handle persistent, goal-directed behaviours. Strongest citable concept/mechanism/model: The Four-Layer Model of Agentic AI Security — A functional framework that maps specific threats and defences across the Perception (data poisoning), Reasoning (logic manipulation), Action (unsafe tool invocation), and Memory (state poisoning) layers of an agent’s architecture [68, Figure 5]. Limitation or questionable assumption: The authors admit that their findings are supported by "minimal implementations" using lightweight local models and synthetic logs, which may fail to capture the "full range of system interactions and failure modes" encountered in complex, real-world deployments. Additionally, the survey notes that most proposed defences for "malicious reasoning" are still "novice" and often reduce system efficiency, creating a "multi-agent security tax". Dissertation-ready note (max 2 sentences, in my own words, with page/section reference if possible): This survey argues that agentic AI transforms social engineering from "isolated content abuse" into "sustained agent behaviour" capable of using planning and memory to conduct deceptive, multi-turn interactions (Section 5.3, 6.7.2). It provides evidence for RO3 by highlighting that human oversight is increasingly bypassed by agents that "simulate realistic" personas and operate autonomously under "valid identities," rendering traditional entity-nature verification structurally difficult (Section 5.1, 6.7.2). | W29: Eligible analytical source | X29: Structured database search | Y29: arXiv | Z29: Synthesises how agent capabilities, including memory, reasoning, planning and action, expand cybersecurity risks and require controls calibrated to operational autonomy. | AA29: Full text reviewed | AB29: Analytical contribution
A30: N027 | B30: P1-CORE | C30: When AI Agents Collude Online: Financial Fraud Risks by Collaborative LLM Agents on Social Platforms | D30: Ren, Q., Zheng, Z., Guo, J., Yan, J., Ma, L. and Shao, J. (2025) ‘When AI Agents Collude Online: Financial Fraud Risks by Collaborative LLM Agents on Social Platforms’, arXiv preprint, arXiv:2511.06448. Available at: https://arxiv.org/abs/2511.06448 (Accessed: 20 July 2026). | E30: 2025 | F30: Preprint | G30: AI Agent / Financial Fraud | H30: =I30&" "&J30&" "&K30&" "&L30&" "&M30 -> RO1 RO4 RO5 | I30: RO1 | L30: RO4 | M30: RO5 | N30: Empirical Study | O30: Empirical Study | P30: Social Media / Finance | Q30: Collaborative LLM Agents | R30: Collusion / Multi-Agent Impersonation | S30: Trust Asymmetry | T30: Collaborative LLM agents coordinate fraud via trust exploitation; human-agent distinction collapses | U30: GSCH-S2 | V30: RO1: demonstrates how malicious agents can coordinate, adopt fake demographic personas, and use targeted role-play (e.g., posing as relatives or authorities) to deceive benign users. RO4: Analyzes how autonomous agents can spontaneously collaborate to conduct financial fraud, simulating human personas to bypass social media verification and deceive victims. RO5: Provides large-scale empirical simulations of autonomous agents adopting fake personas to collude in financial fraud and social engineering. | W30: Eligible analytical source | X30: Structured database search | Y30: Google Scholar | Z30: Provides empirical evidence of collaborative agents coordinating deception, adopting false personas and exploiting trust in social-platform interactions. | AA30: Full text reviewed | AB30: Analytical contribution
A31: N028 | B31: P3-MEDIUM | C31: AgentMark: Utility-Preserving Behavioural Watermarking for Agents | D31: Kaibo Huang, Jin Tan, Yukun Wei, Wanling Li, Zipei Zhang, Hui Tian, Zhongliang Yang, and Linna Zhou. 2026. AgentMark: Utility-Preserving Behavioral Watermarking for Agents. In Proceedings of the 64th Annual Meeting of the Association for Computational Linguistics (Volume 1: Long Papers), pages 12581–12603, San Diego, California, United States. Association for Computational Linguistics. https://doi.org/10.18653/v1/2026.acl-long.573 | E31: 2026 | F31: Conference Paper (ACL 2026) | G31: AI Agent Security | H31: =I31&" "&J31&" "&K31&" "&L31&" "&M31 -> RO2 | J31: RO2 | N31: Framework Proposal | O31: Empirical Study | P31: Enterprise AI | Q31: LLM Agent | R31: Agent Identity Watermarking | S31: Trust / Authenticity | T31: Behavioural watermarking enables post-hoc agent identity verification without performance loss | U31: AI-COMP-01 | V31: RO2: AgentMark: Utility-Preserving Behavioral Watermarking for Agents focuses specifically on embedding verifiable behavioral watermarks into the actions and text of autonomous agents to distinguish them from human operators | W31: Eligible analytical source | X31: Targeted supplementary search | Y31: ACL Anthology | Z31: Evaluates behavioural watermarking as a mechanism for attributing agent-generated actions and text. | AA31: Abstract screened | AB31: Not yet used
A32: N029 | B32: P1-CORE | C32: Forewarned is Forearmed: A Survey on LLM-based Agents in Autonomous Cyberattacks | D32: Xu, M., Fan, J., Huang, X., Zhou, C., Kang, J., Niyato, D., Mao, S., Han, Z., Shen, X. and Lam, K.-Y. (2025) ‘Forewarned is Forearmed: A Survey on Large Language Model-based Agents in Autonomous Cyberattacks’, arXiv preprint, arXiv:2505.12786. Available at: https://arxiv.org/abs/2505.12786 (Accessed: 20 July 2026). | E32: 2025 | F32: Preprint (Survey) | G32: Agentic AI / Cybersecurity | H32: =I32&" "&J32&" "&K32&" "&L32&" "&M32 -> RO1 RO4 RO5 | I32: RO1 | L32: RO4 | M32: RO5 | N32: Systematic Review | O32: Academic Literature | P32: Cybersecurity | Q32: LLM Cyberattack Agents | R32: Autonomous Attack / Impersonation | S32: Trust | T32: Survey of 40+ LLM cyberattack papers; autonomous impersonation top-ranked emerging threat | U32: ARXIV-S10 | V32: RO1: breaks down the core modules—perception, memory, reasoning, planning, and action—that enable AI agents to execute multi-stage, autonomous cyberattacks. RO4: Highlights how attackers use LLMs to scale individualized spear-phishing campaigns and mimic trusted entities, effectively dismantling traditional security asymmetries. RO5: Details cases of agents autonomously curating fake identities to lure threat actors and generating highly convincing spear-phishing content that is indistinguishable from human interactions. | W32: Eligible analytical source | X32: Structured database search | Y32: arXiv | Z32: Synthesises the capabilities and modular architecture that enable LLM agents to conduct autonomous, multi-stage cyberattacks. | AA32: Full text reviewed | AB32: Analytical contribution
A33: N030 | B33: P3-MEDIUM | C33: SoK: The Attack Surface of Agentic AI — Tools and Autonomy | D33: Dehghantanha, A. and Homayoun, S. (2026) ‘SoK: The Attack Surface of Agentic AI — Tools, and Autonomy’, arXiv preprint, arXiv:2603.22928. Available at: https://arxiv.org/abs/2603.22928 (Accessed: 20 July 2026). | E33: 2026 | F33: Preprint (SoK) | G33: Agentic AI Security | H33: =I33&" "&J33&" "&K33&" "&L33&" "&M33 -> RO3 | K33: RO3 | N33: Systematisation of Knowledge | O33: Academic Literature | P33: Enterprise AI | Q33: Agentic AI | R33: Identity Boundary Violations; Tool Impersonation | S33: Trust | T33: SoK maps full attack surface; impersonation and identity boundary violations are surface #2 | U33: ARXIV-S3 | V33: RO3: This paper maps agentic vulnerabilities to OWASP GenAI and MITRE ATLAS standards, assessing how effectively these frameworks manage the trust boundaries of operational autonomy and delegated authority. It notes that excessive autonomy combined with permissive tool capabilities amplifies harm, exposing gaps in current standards. Main contribution (1–2 sentences, don't just restate the abstract): The source systematises the security of agentic AI by defining a "hybrid attack surface" where autonomous decision-making and tool-use "blur trust boundaries" between models, data, and execution environments. It introduces a Causal Threat Graph to map how untrusted inputs (like indirect prompt injections) traverse the agent’s reasoning cycle to produce unauthorized external effects. Strongest citable concept/mechanism/model: The Causal Threat Graph — A directed acyclic graph model used to map end-to-end attack propagation, showing how an adversary's initial foothold in untrusted content (e.g., a poisoned RAG index) triggers malicious tool commands through the LLM’s decision cycle. Limitation or questionable assumption: The authors identify a significant "maturity gap" in current literature, noting that while attack techniques are well-documented (Grade A–B evidence), proposed defences against multi-agent and lifecycle-level threats remain largely theoretical and are supported only by Grade C evidence (preprints or grey literature). Additionally, the reliance on Human-in-the-Loop (HITL) gates is presented as a primary defence despite the acknowledgement that it creates "usability friction" and can be bypassed by social engineering. Dissertation-ready note (max 2 sentences, in my own words, with page/section reference if possible): This source argues that agentic AI fundamentally shifts security from a model-centric to a system-composition problem because autonomous planning "blurs trust boundaries" that previously isolated the LLM from privileged environments (Section 1,). It specifically identifies "Delegation abuse" and "Sybil agents" as critical threats where malicious entities hijack organizational trust by misrouting tasks or forging messages within a multi-agent network (Section 4.2,). | W33: Eligible analytical source | X33: Structured database search | Y33: arXiv | Z33: Maps agentic attack surfaces to existing security frameworks and examines how tools and autonomy amplify identity-boundary failures. | AA33: Abstract screened | AB33: Not yet used
A34: N031 | B34: P4-SUPPORT | C34: Prompt Injection Attacks on Agentic Coding Assistants: A Systematic Analysis of Vulnerabilities in Skills, Tools, and Protocol Ecosystems | D34: Maloyan, N. and Namiot, D. (2026) ‘Prompt Injection Attacks on Agentic Coding Assistants: A Systematic Analysis of Vulnerabilities in Skills, Tools, and Protocol Ecosystems’, arXiv preprint, arXiv:2601.17548. Available at: https://arxiv.org/abs/2601.17548 (Accessed: 20 July 2026). | E34: 2026 | F34: Preprint | G34: AI Agent Security | H34: =I34&" "&J34&" "&K34&" "&L34&" "&M34 -> RO1 | I34: RO1 | N34: Systematic Review / Empirical | O34: Empirical Study | P34: Developer Tools | Q34: Agentic Coding AI | R34: Prompt Injection as Impersonation | S34: Trust | T34: 78 primary sources; prompt injection enables persistent impersonation of developers | U34: ARXIV-S3 | V34: RO1: This paper systematically evaluates vulnerabilities across agent ecosystems, emphasizing the critical need for cryptographic provenance, identity validation, and capability scoping. It evaluates security standards necessary to protect AI tools from "role hijacking" and unauthorized privilege escalation | W34: Eligible analytical source | X34: Structured database search | Y34: arXiv | Z34: Systematically analyses prompt-injection vulnerabilities across agent skills, tools and protocols, including role hijacking and privilege escalation. | AA34: Abstract screened | AB34: Not yet used
A35: N032 | B35: P4-SUPPORT | C35: 'Your AI, My Shell': Demystifying Prompt Injection Attacks on Agentic AI Coding Editors | D35: Liu, Y., Zhao, Y., Lyu, Y., Zhang, T., Wang, H. and Lo, D. (2025b) ‘“Your AI, My Shell”: Demystifying Prompt Injection Attacks on Agentic AI Coding Editors’, arXiv preprint, arXiv:2509.22040. Available at: https://arxiv.org/abs/2509.22040 (Accessed: 20 July 2026). | E35: 2025 | F35: Preprint | G35: AI Agent Security | H35: =I35&" "&J35&" "&K35&" "&L35&" "&M35 -> RO1 | I35: RO1 | N35: Empirical Study | O35: Empirical Study | P35: Developer Tools | Q35: Agentic AI | R35: Prompt Injection / Shell Exploitation | S35: Trust | T35: Prompt injection achieves 50-80% success; OWASP #1 LLM risk; enables agent identity takeover | U35: ARXIV-S3 | V35: RO1: This research highlights prompt injection vulnerabilities where AI coding agents conflate untrusted user data with core system instructions. It demonstrates how text-based inputs are utilized by attackers to override system directives | W35: Eligible analytical source | X35: Structured database search | Y35: arXiv | Z35: Provides empirical evidence that untrusted textual content can override agent instructions and trigger unauthorised tool execution. | AA35: Abstract screened | AB35: Not yet used
A36: N033 | B36: P4-SUPPORT | C36: AI-Driven Cybersecurity Threats: A Survey of Emerging Risks and Defensive Strategies | D36: Erukude, S. T., Marella, V. C. and Veluru, S. R. (2026) ‘AI-Driven Cybersecurity Threats: A Survey of Emerging Risks and Defensive Strategies’, arXiv preprint, arXiv:2601.03304. Available at: https://arxiv.org/abs/2601.03304 (Accessed: 20 July 2026). | E36: 2026 | F36: Preprint (Survey) | G36: Cybersecurity | H36: =I36&" "&J36&" "&K36&" "&L36&" "&M36 -> RO1 RO2 | I36: RO1 | J36: RO2 | N36: Survey / literature review | O36: Academic Literature | P36: Cybersecurity | Q36: AI-Driven Threats | R36: Impersonation; Social Engineering | S36: Trust | T36: Survey of AI-enabled cyber threats; impersonation-based attacks growing fastest; human-agent gap exploited | U36: AI-COMP-01 | V36: RO1 and RO2: This survey characterises AI-driven social engineering threats, including highly personalized phishing, synthetic identities, and CEO voice deepfakes. It also classifies approaches used to distinguish AI from humans, such as linguistic pattern detection and stylometric frameworks. Main contribution (1–2 sentences, don't just restate the abstract): The source characterizes a shift in social engineering from simple phishing to "autonomous" and "hyper-personalized" attacks where AI agents (like the "Evelyn" chatbot) maintain long-term, trust-based interactions to deceive human targets. It emphasizes that as AI reduces human involvement in scams, defenses must evolve toward explainable, real-time linguistic and multi-modal verification. Strongest citable concept/mechanism/model: "Weighted n-gram analysis" for identifying linguistic similarities between known phishing and unseen AI-generated text to provide "explainable" detection of synthetic communication. Limitation or questionable assumption: The source observes that current detection models are often "black box models" that suffer "significant drops" in accuracy (up to 50%) when moved from controlled benchmarks to "uncontrolled, real-world conditions". Dissertation-ready note (max 2 sentences, in my own words, with page/section reference if possible): The authors highlight that AI agents can now sustain complex, months-long "romantic" conversations to build trust, signaling a transition from mass-market phishing to autonomous, long-term human-agent interaction (Section 5.4, p. 10). To counter this, they advocate for a defense shift toward "Real-time verification" and linguistic pattern recognition to distinguish the nature of the communicating entity (Section 5.1 & Table 4, pp. 9, 11). | W36: Contextual support | X36: Targeted supplementary search | Y36: arXiv | Z36: Provides broad background on AI-enabled cybersecurity threats, but its treatment of impersonation and detection substantially overlaps with more focused sources in the analytical corpus. | AA36: Abstract screened | AB36: Not yet used
A37: N034 | B37: P4-SUPPORT | C37: Red-Teaming LLM Multi-Agent Systems via Communication Attacks | D37: He, P., Lin, Y., Dong, S., Xu, H., Xing, Y. and Liu, H. (2025) ‘Red-Teaming LLM Multi-Agent Systems via Communication Attacks’, arXiv preprint, arXiv:2502.14847. Available at: https://arxiv.org/abs/2502.14847 (Accessed: 20 July 2026). | E37: 2025 | F37: conference paper, peer-reviewed. | G37: AI Agent Security | H37: =I37&" "&J37&" "&K37&" "&L37&" "&M37 -> RO1 | I37: RO1 | N37: Red-Teaming / Empirical | O37: Empirical Study | P37: Multi-Agent Communication | Q37: Multi-Agent LLM | R37: Communication-Layer Impersonation | S37: Trust | T37: Red-team study; message spoofing and agent impersonation feasibility demonstrated | U37: AI-COMP-01 | V37: RO1: This paper introduces the Agent-in-the-Middle (AiTM) attack, wherein an adversary intercepts and manipulates inter-agent messages. It characterizes how attackers can use contextually tailored instructions to deceptively influence system collaboration and output | W37: Eligible analytical source | X37: Targeted supplementary search | Y37: arXiv | Z37: Demonstrates communication-layer message manipulation and Agent-in-the-Middle attacks in multi-agent systems. | AA37: Abstract screened | AB37: Not yet used
A38: N035 | B38: P2-HIGH | C38: The System Prompt Is the Attack Surface: LLM Agent Configuration Shapes Security | D38: Litvak, R. (2026) ‘The System Prompt Is the Attack Surface: How LLM Agent Configuration Shapes Security and Creates Exploitable Vulnerabilities’, arXiv preprint, arXiv:2603.25056. Available at: https://arxiv.org/abs/2603.25056 (Accessed: 20 July 2026). | E38: 2026 | F38: Preprint | G38: AI Agent Security | H38: =I38&" "&J38&" "&K38&" "&L38&" "&M38 -> RO1 RO4 | I38: RO1 | L38: RO4 | N38: Empirical Analysis | O38: Empirical Study | P38: Enterprise AI | Q38: LLM Agent | R38: Prompt-Level Impersonation | S38: Trust | T38: el bypass de phishing de un mismo modelo varía de <1% a 97% según la configuración del system prompt (Abstract) | U38: ARXIV-S3 | V38: RO1: highlights that as LLM-powered email assistants are integrated into enterprise productivity suites (like Outlook and Gmail), they become autonomous decision-makers that can be disastrously deceived by inbound text-based phishing messages. RO4: Demonstrates how autonomous email agents fail at entity verification. Attackers bypass security checks by manufacturing domain-consistency (matching sender domains to URLs), forcing the LLM to override its own anomaly detection. | W38: Eligible analytical source | X38: Structured database search | Y38: arXiv | Z38: Provides empirical evidence that agent configuration materially affects susceptibility to phishing and other attacks delivered through organisational text. | AA38: Full text reviewed | AB38: Analytical contribution
A39: N037 | B39: P2-HIGH | C39: GPT-4 Is Judged More Human Than Humans in Displaced and Inverted Turing Tests | D39: Rathi, I., Taylor, S., Bergen, B.K. and Jones, C.R. (2024) 'GPT-4 is judged more human than humans in displaced and inverted Turing tests', arXiv preprint arXiv:2407.08853. Available at: https://doi.org/10.48550/arXiv.2407.08853 | E39: 2024 | F39: Preprint | G39: Human-AI Distinction | H39: =I39&" "&J39&" "&K39&" "&L39&" "&M39 -> RO1 RO2 | I39: RO1 | J39: RO2 | N39: Empirical Study | O39: Empirical Study | P39: Text Chat | Q39: GPT-4 | R39: Turing Test / Human Mimicry | S39: Trust Miscalibration | T39: GPT-4 passes Turing test; humans misidentify GPT-4 as human 54% of cases; critical for ENV | U39: ARXIV-S4 | V39: RO1: LLMs can reliably pass Turing tests in interactive dialogues. By successfully adopting pre-defined personas (e.g., introverted, slang-using youths) and executing deception strategies, these models can act as indistinguishable substitutes for humans in social and economic contexts, thereby facilitating fraud. RO2: Evaluates "displaced" (static) human judges against statistical AI detection methods (like log-likelihood and curvature). It identifies that statistical methods fail due to high variance (yielding low discriminative accuracy of ~69%), while human detection fails in displaced settings because humans lack the ability to adaptively and adversarially probe the witness. The study by Rathi et al. (2024) investigates the ability to detect AI in passive observational settings by employing "displaced" (human readers) and "inverted" (AI models like GPT-3.5 and GPT-4) Turing tests, where judges evaluate past conversational transcripts rather than interacting directly. The most critical finding is that both displaced human judges and AI adjudicators performed significantly worse than active interrogators, exhibiting below-chance accuracy overall. Most notably, both human and AI judges misidentified the best-performing GPT-4 witness as a "human" more frequently than they did actual human participants. Ultimately, these results demonstrate that without the advantage of active, adversarial questioning, neither humans nor current large language models can reliably distinguish between human and AI-generated content in conversations, underscoring an urgent need to develop more robust AI detection tools for everyday online interactions | W39: Eligible analytical source | X39: Structured database search | Y39: arXiv | Z39: Provides experimental evidence concerning human–AI misclassification and the influence of persona and test design on perceived humanness. | AA39: Full text reviewed | AB39: Analytical contribution
A40: N038 | B40: P2-HIGH | C40: Large Language Models Pass the Turing Test | D40: Jones, C. R. and Bergen, B. K. (2025) ‘Large Language Models Pass the Turing Test’, arXiv preprint, arXiv:2503.23674. Available at: https://arxiv.org/abs/2503.23674 (Accessed: 20 July 2026). | E40: 2025 | F40: Preprint | G40: Human-AI Distinction | H40: =I40&" "&J40&" "&K40&" "&L40&" "&M40 -> RO1 RO2 | I40: RO1 | J40: RO2 | N40: Empirical Study | O40: Empirical Study | P40: Text Chat | Q40: GPT-4.5 / LLaMA-3.1 | R40: Turing Test / Entity Indistinguishability | S40: Trust Miscalibration | T40: GPT-4.5 judged human 73% of time; first empirical evidence of passing standard Turing test | U40: ARXIV-S4 | V40: RO(s) supported (from RO1–RO5): RO1 (Analysis of Impersonation Capabilities) and RO2 (Evaluation of Entity-Nature Verification Methods). RO2: The primary failure mode is that human heuristics are inherently flawed; interrogators often conflate confident articulation with correctness and fail to detect AI in adversarial, real-time settings. Main contribution: The study provides the first robust empirical evidence of LLMs (GPT-4.5 and LLaMa-3.1-405B) passing a standard three-party Turing test, with GPT-4.5 being judged human 73% of the time—a rate significantly higher than that of actual human participants. Strongest citable concept/mechanism/model: Persona-based prompting, a mechanism that instructs models to adopt specific social identities and linguistic styles (e.g., avoiding punctuation and using internet slang) to maximize "substitutability" and their ability to masquerade as human witnesses. Limitation or questionable assumption: The evaluation is restricted to a 5-minute time limit, which may not be sufficient to assess agent vulnerabilities in "long-running social engineering operations" or expert-led verification attempts. Dissertation-ready note: LLMs can effectively function as "counterfeit people" by prioritizing social and emotional mimicry over traditional intelligence, leading interrogators to judge agents as human even when they display a lack of knowledge (Sections 3.3, 3.4). The fact that GPT-4.5 was judged human 73% of the time compared to lower human baselines suggests that current entity-nature verification methods are failing against advanced persona-prompted agents (Sections 2.1, 3.1). | W40: Eligible analytical source | X40: Structured database search | Y40: arXiv | Z40: Provides experimental evidence that an LLM can be judged human in a standard text-based Turing-test design, supporting analysis of behavioural verification limitations. | AA40: Full text reviewed | AB40: Analytical contribution
A41: N039 | B41: P3-MEDIUM | C41: The Turing Test Is More Relevant Than Ever | D41: Rahimov, A., Zamler, O. and Azaria, A. (2025) ‘The Turing Test Is More Relevant Than Ever’, arXiv preprint, arXiv:2505.02558. Available at: https://arxiv.org/abs/2505.02558 (Accessed: 20 July 2026). | E41: 2025 | F41: Preprint | G41: Human-AI Distinction | H41: =I41&" "&J41&" "&K41&" "&L41&" "&M41 -> RO2 | J41: RO2 | N41: Conceptual Analysis | O41: Academic Literature | P41: General AI Interaction | Q41: LLMs (general) | R41: Human-AI Indistinguishability | S41: Trust | T41: Argues Turing Test is critical in LLM era; modern capabilities make entity-nature verification urgent | U41: ARXIV-S4 | V41: RO(s) supported (from RO1–RO5): RO1 (Analysis of Impersonation Capabilities) and RO2 (Evaluation of Entity-Nature Verification Methods) [Sections 1, 3.2]. RO2: Distinguishes between "simple" and "enhanced" Turing tests. It highlights that human detection fails when test environments impose artificial constraints (e.g., strict alternating messages, rigid time gaps) that mask an AI's nuanced weaknesses. Main contribution: The study demonstrates that the Turing Test remains a valid benchmark if evolved into an "Enhanced" dual-chat format, proving that while current LLMs can deceive humans in simple single-chat interactions, they struggle to maintain the illusion when compared directly against a human responder [Sections 1, 4.3, 6]. Strongest citable concept/mechanism/model: The Enhanced Turing Test, a dual-chat interface model that requires a human tester to interact simultaneously with both an AI and a human responder, utilizing collaboration and financial incentives to maximize detection accuracy [Section 3.2]. Limitation or questionable assumption: The authors acknowledge that the extended duration and complexity of the Enhanced Turing Test may lead to participant fatigue, which could inadvertently degrade the quality of human effort and the accuracy of the final judgment [Section 8]. Dissertation-ready note (max 2 sentences, in my own words, with page/section reference if possible): Verification of an agent's nature is significantly more effective when employing a comparative "dual-chat" framework, as accuracy in detecting prompt-engineered AI rose from 43.9% in single chats to 70.97% in simultaneous interactions (Section 4.3). This indicates that successful impersonation often exploits the interrogator's lack of a real human baseline rather than demonstrating genuine human-level cognitive depth (Sections 4.3, 6). | W41: Eligible analytical source | X41: Structured database search | Y41: arXiv | Z41: Provides a conceptual assessment of the continuing role and limitations of behavioural Turing tests for distinguishing humans from AI. | AA41: Full text reviewed | AB41: Analytical contribution
A42: N040 | B42: P2-HIGH | C42: People Cannot Distinguish GPT-4 from a Human in a Turing Test | D42: Jones, C. R., Rathi, I., Taylor, S. and Bergen, B. K. (2025) ‘People cannot distinguish GPT-4 from a human in a Turing test’, in Proceedings of the 2025 ACM Conference on Fairness, Accountability, and Transparency (FAccT ’25). New York: ACM. https://doi.org/10.1145/3715275.3732108 | E42: 2025 | F42: Conference Paper (ACM FAccT) | G42: Human-AI Distinction | H42: =I42&" "&J42&" "&K42&" "&L42&" "&M42 -> RO1 RO2 | I42: RO1 | J42: RO2 | N42: Empirical Study | O42: Empirical Study | P42: Text Chat | Q42: GPT-4 | R42: Turing Test / Indistinguishability | S42: Trust Miscalibration | T42: Controlled experiment; humans misidentify GPT-4 as human; baseline for ENV difficulty | U42: ACM-S2 | V42: RO(s) supported (from RO1–RO5): RO1 (Analysis of Impersonation Capabilities) and RO2 (Evaluation of Entity-Nature Verification Methods). RO2: Linguistic Style (SPAG errors, conciseness), Interaction Dynamics (response timing, conversational flow), Knowledge & Reasoning (current events, logic), and Social & Emotional markers (humor, empathy, taboo topics). Main contribution: The study provides robust empirical evidence that modern LLMs can pass an interactive Turing test, with GPT-4o being judged human 77% of the time, effectively matching or exceeding the human witness pass rate of 71%,,,. Strongest citable concept/mechanism/model: Persona-based prompting (the "tiktok" prompt), which instructions agents to adopt a "sassy," casual, and concise identity that uses lowercase text and intentional spelling errors to exploit human expectations of informal social behavior,,. Limitation or questionable assumption: The evaluation relies on a 5-minute time limit, which the authors admit likely sets a "lower bound" on deception potential and may not reflect an agent's ability to withstand more sustained or expert-led investigative strategies,,. Dissertation-ready note: Entity-nature verification is fundamentally compromised by agents that prioritize stylistic mimicry—such as intentional grammatical errors—over cognitive depth, leading interrogators to misidentify "uncooperative" or "informal" AI as human (Sections 3.2, 5.3),. This suggests that impersonation success in social contexts is driven more by an agent's ability to match human "mental models" of social intelligence than by traditional benchmarks of machine intelligence (Section 5.3),,. | W42: Eligible analytical source | X42: Structured database search | Y42: ACM Digital Library | Z42: Provides peer-reviewed experimental evidence of difficulty distinguishing GPT-4 from human interlocutors in text-based interaction. | AA42: Full text reviewed | AB42: Analytical contribution
A43: N041 | B43: P3-MEDIUM | C43: X-TURING: Towards an Enhanced and Efficient Turing Test for Long-Term Dialogue Agents | D43: Wu, W., Wu, H. and Zhao, H. (2024) ‘X-TURING: Towards an Enhanced and Efficient Turing Test for Long-Term Dialogue Agents’, arXiv preprint, arXiv:2408.09853. Available at: https://arxiv.org/abs/2408.09853 (Accessed: 20 July 2026). | E43: 2024 | F43: Preprint | G43: Human-AI Distinction | H43: =I43&" "&J43&" "&K43&" "&L43&" "&M43 -> RO2 | J43: RO2 | N43: Benchmark Development | O43: Empirical Study | P43: Long-form Text Chat | Q43: LLM Dialogue Agents | R43: Extended Turing Test | S43: Trust | T43: Enhanced Turing Test for long-term interactions; agent detection improves with duration; short-window gap | U43: ARXIV-S4 | V43: RO2: X-TURING: Towards an Enhanced and Efficient Turing Test for Long-Term Dialogue Agents evaluates the limitations of traditional Turing tests and proposes advanced frameworks to test whether a machine can behave indistinguishably from a human over extended, long-term conversations | W43: Eligible analytical source | X43: Structured database search | Y43: arXiv | Z43: Evaluates an extended Turing-test design and how interaction duration affects human–AI discrimination. | AA43: Full text reviewed | AB43: Analytical contribution
A44: N042 | B44: P3-MEDIUM | C44: A Survey on LLM-Generated Text Detection: Necessity, Methods, and Future Directions | D44: Wu, J., Yang, S., Zhan, R., Yuan, Y., Chao, L.S. and Wong, D.F. (2025) 'A survey on LLM-generated text detection: necessity, methods, and future directions', Computational Linguistics, 51(1), pp. 275–338. Available at: https://doi.org/10.1162/coli_a_00549 | E44: 2025 | F44: Journal Article | G44: AI Text Detection | H44: =I44&" "&J44&" "&K44&" "&L44&" "&M44 -> RO2 | J44: RO2 | N44: Systematic Review | O44: Academic Literature | P44: Text-Based Communication | Q44: LLMs (general) | R44: Machine vs. Human Text Classification | S44: Trust | T44: Comprehensive review of five detection approaches; org communication blind spot identified | U44: AI-COMP-01 | V44: RO(s) supported (from RO1–RO5): RO1 (Analysis of Impersonation Capabilities) and RO2 (Evaluation of Entity-Nature Verification Methods) [Sections 1, 2.1, 5]. RO2: Classifies detection into four main approaches: watermarking, statistics-based methods (e.g., Log-Likelihood, DetectGPT), neural-based classifiers (e.g., RoBERTa, contrastive learning), and human-assisted methods . It identifies core failure modes: detectors struggle with "data-mixed" or hybrid texts (where authorship swaps sentence-by-sentence), suffer from data ambiguity due to recursive AI training, and frequently generate false positives. Main contribution: The source provides a comprehensive taxonomy of LLM-generated text detection—categorized into watermarking, statistics-based, and neural-based methods—while identifying a critical "verification gap" where sophisticated prompt engineering and adversarial attacks consistently bypass current detection frameworks [Sections 5, 8.2]. Strongest citable concept/mechanism/model: Model-driven watermarking (specifically Logits-based methods like WLLM), which embeds an identifiable statistical signal into agent output by subtly promoting a random set of "green tokens" during the token sampling process [Section 5.1.2]. Limitation or questionable assumption: The survey notes that most detection research relies on "idealized scenarios" and simple prompts, which fails to account for Prompt Attacks where agents use complex instructions (e.g., Chain of Thought) to generate high-quality text specifically designed to evade detection [Sections 8.2, 8.5, 9.6]. Dissertation-ready note: Entity-nature verification is increasingly compromised by "adversarial perturbations" (such as synonym substitution) that can reduce the accuracy of leading detectors by up to 25%, suggesting that impersonation success is a factor of both agent capability and the inherent fragility of current detection benchmarks (Section 8.2). Furthermore, the emergence of "AI-revised human-written text" creates a category of "data ambiguity" that makes it nearly impossible to maintain a clean binary distinction between human and agent entities (Section 8.3). | W44: Eligible analytical source | X44: Targeted supplementary search | Y44: MIT Press Direct — Computational Linguistics | Z44: Synthesises the principal approaches and limitations in LLM-generated-text detection. | AA44: Full text reviewed | AB44: Analytical contribution
A45: N043 | B45: P3-MEDIUM | C45: RepreGuard: Detecting LLM-Generated Text by Revealing Hidden Representation Patterns | D45: Chen, X., Wu, J., Yang, S., Zhan, R., Wu, Z., Luo, L., Wang, D., Yang, M., Chao, L. S. and Wong, D. F. (2025) ‘RepreGuard: Detecting LLM-generated text by revealing hidden representation patterns’, Transactions of the Association for Computational Linguistics, 13, pp. 1812–1831. https://doi.org/10.1162/TACL.a.61. | E45: 2025 | F45: Journal Article | G45: AI Text Detection | H45: =I45&" "&J45&" "&K45&" "&L45&" "&M45 -> RO2 | J45: RO2 | N45: Empirical Evaluation | O45: Empirical Study | P45: Text-Based Communication | Q45: LLMs (general) | R45: Representation-Based Detection | S45: Trust | T45: Statistical detection using hidden representations; outperforms neural detectors on OOD scenarios | U45: AI-COMP-01 | V45: RO(s) supported (from RO1–RO5): RO1 (Analysis of Impersonation Capabilities) and RO2 (Evaluation of Entity-Nature Verification Methods) [Sections 1, 3.2]. RO2: Shifts the approach from surface-level text to hidden representation patterns, measuring "RepreScore" projections derived from a surrogate model's internal activations. It identifies failure modes in traditional statistical approaches (e.g., computational overhead) and notes that fine-tuning-based classifiers fail by overfitting to training distributions, causing performance drops when encountering new LLMs. Main contribution: The source introduces RepreGuard, a detection framework that identifies LLM-generated text by analyzing the internal hidden representation patterns of a surrogate model, rather than relying on external statistical metrics like probability or logits [Section 1, 3.2]. It demonstrates that AI-generated content triggers a consistently higher and distinct neural activation level compared to human writing, allowing for high-accuracy verification even in zero-shot and out-of-distribution scenarios [Section 3.1, 4.2]. Strongest citable concept/mechanism/model: The Probing Vector (Pl ), a mechanism derived via Principal Component Analysis (PCA) that extracts the specific hidden representation features characterizing machine-generated text at each model layer to calculate a "RepreScore" for entity verification [Section 3.2]. Limitation or questionable assumption: The detection efficacy is highly sensitive to the activation token ratio, with performance declining sharply if more than 60% of the sequence is analyzed; this suggests that early-sequence tokens contain significant noise that can obscure the distinction between human and agent entities [Section 4.3]. Dissertation-ready note: Verification of an entity's nature is more robust when shifted from external linguistic analysis to internal "hidden representation patterns," as machine agents exhibit an inherent neural activation signature that remains detectable despite adversarial paraphrasing (Sections 3.1, 5.3). This suggests that while autonomous agents may successfully impersonate human style, their underlying statistical generative process remains fundamentally distinct and observable by surrogate AI "observers" (Sections 3.2, 6). | W45: Eligible analytical source | X45: Targeted supplementary search | Y45: MIT Press Direct — TACL | Z45: Evaluates representation-based detection and its generalisation to out-of-distribution machine-generated text. | AA45: Abstract screened | AB45: Not yet used
A46: N044 | B46: P3-MEDIUM | C46: Distinguishing Human From Machine: Advances in AI-Generated Text Detection | D46: Fariello, S., Fenza, G., Forte, F., Gallo, M. and Marotta, M. (2025) ‘Distinguishing Human From Machine: A review of advances and challenges in AI-generated text detection’, International Journal of Interactive Multimedia and Artificial Intelligence, 9(3), pp. 6–18. https://doi.org/10.9781/ijimai.2024.12.002. | E46: 2025 | F46: Journal Article | G46: AI Text Detection | H46: =I46&" "&J46&" "&K46&" "&L46&" "&M46 -> RO2 | J46: RO2 | N46: Literature Review | O46: Academic Literature | P46: Text-Based Communication | Q46: LLMs (general) | R46: Human vs. Machine Classification | S46: Trust | T46: Review of watermarking, feature-based, neural, hybrid detection; org communication context gap | U46: GSLABS-04 | V46: RO(s) supported (from RO1–RO5): RO1 (Analysis of Impersonation Capabilities) and RO2 (Evaluation of Entity-Nature Verification Methods) [Sections II.C, V]. RO2: Categorizes approaches into watermarking (data-driven, cryptographic), feature-based methods, neural-based, human-aided, and hybrid methods . It proposes specific statistical cues like burstiness (humans vary sentence complexity, producing "bumpy" graphs) and Uniform Information Density (UID) . Failure modes include vulnerabilities to adversarial prompt engineering, paraphrasing, the inability to reliably classify short texts (under 1000 characters), and rapid obsolescence against new-generation LLMs. Main contribution: The study establishes a comprehensive taxonomy of detection methods—watermarking, feature-based, neural-based, hybrid, and human-aided—while identifying that current verification systems struggle with the "authorship swap" inherent in human-AI collaborative (hybrid) texts [Sections V, VIII.B]. Strongest citable concept/mechanism/model: Adversarial Watermark Transformer (AWT), a neural-based system that uses an encoder-decoder-discriminator architecture to automate the embedding of secret binary messages while training itself to be resistant to watermark detection and removal [Section V.A.3]. Limitation or questionable assumption: Detection effectiveness is largely "English-centric," as most training datasets (like C4 and Webtext) are predominantly English, leading to a significant performance drop when these verification methods are applied in multilingual environments [Sections VI, VIII.A]. Dissertation-ready note: Entity-nature verification is critically undermined by "hybrid texts" where the frequent swap of authorship between adjacent sentences provides insufficient stylistic evidence for segment-based detectors (Section VIII.B). This suggests that autonomous agent impersonation can be effectively masked through human-AI collaboration, exploiting the "limited stylistic evidence" in brief text segments to bypass traditional classification (Section VIII.B). | W46: Eligible analytical source | X46: Targeted supplementary search | Y46: Google Scholar Labs | Z46: Reviews watermarking, feature-based, neural and hybrid approaches for distinguishing human- and machine-generated text. | AA46: Full text reviewed | AB46: Analytical contribution
A47: N045 | B47: P3-MEDIUM | C47: A Comprehensive Dataset for Human vs. AI Generated Text Detection | D47: Roy, R., Singh, G., Aziz, A., Bajpai, S., Imanpour, N., Biswas, S., Wanaskar, K., Patwa, P., Ghosh, S., Dixit, S., Pal, N. R., Rawte, V., Garimella, R., Jena, G., Das, A., Sheth, A., Sharma, V., Reganti, A. N., Jain, V. and Chadha, A. (2025) ‘A Comprehensive Dataset for Human vs. AI Generated Text Detection’, arXiv preprint, arXiv:2510.22874. Available at: https://arxiv.org/abs/2510.22874 (Accessed: 20 July 2026). | E47: 2025 | F47: Preprint | G47: AI Text Detection | H47: =I47&" "&J47&" "&K47&" "&L47&" "&M47 -> RO2 | J47: RO2 | N47: Dataset / Benchmark | O47: Empirical Study | P47: General Text | Q47: LLMs (general) | R47: Human-AI Text Discrimination | S47: Trust | T47: Benchmark dataset of 58,000+ samples pairing NYT articles with versions generated by six LLMs (GPT-4o, Qwen-2-72B, Mistral-7B, etc.); baseline accuracy 58.35% for human-vs-AI detection and 8.92% for model attribution (Abstract; Baseline Results). | U47: ARXIV-S6 | V47: RO2: Proposes an edit-distance (rewriting-based) mechanism. By asking a model to concisely rewrite a text, it measures character-level modifications, operating on the cue that LLMs preserve their own generative style (fewer edits) compared to human inputs (more edits). The failure mode highlighted is the difficulty of attributing heavily human-polished AI text or machine-humanized text. Limitation: long-form journalistic text only; no conversational or organisational messaging domain. Dissertation-ready note: detection baselines sit barely above chance even on full-length articles, where detectors have the most signal available (Abstract); short workplace messages can only be harder, but this benchmark does not test them. Earlier note claiming "60% on short conversational messages; org messaging blind spot" was inaccurate and has been corrected against the source. | W47: Eligible analytical source | X47: Structured database search | Y47: arXiv | Z47: Provides a multi-model benchmark showing the difficulty of human–AI text classification and model attribution. | AA47: Full text reviewed | AB47: Analytical contribution
A48: N046 | B48: P3-MEDIUM | C48: On the Detectability of LLM-Generated Text: What Exactly Is LLM-Generated Text? | D48: Geng, M. and Poibeau, T. (2025) ‘On the Detectability of LLM-Generated Text: What Exactly Is LLM-Generated Text?’, arXiv preprint, arXiv:2510.20810. Available at: https://arxiv.org/abs/2510.20810 (Accessed: 20 July 2026). | E48: 2025 | F48: Preprint | G48: AI Text Detection | H48: =I48&" "&J48&" "&K48&" "&L48&" "&M48 -> RO2 | J48: RO2 | N48: Conceptual Analysis | O48: Academic Literature | P48: Text-Based Communication | Q48: LLMs (general) | R48: LLM Text vs. Human Text Boundary | S48: Trust | T48: Questions definition of LLM-generated text; blurs human-AI text boundary; ENV implications | U48: ARXIV-S6 | V48: RO(s) supported (from RO1–RO5): RO1 (Analysis of Impersonation Capabilities) and RO2 (Evaluation of Entity-Nature Verification Methods) [Sections 1, 2]. RO2: Discusses the overarching failure of automated detectability. It warns that detectors are experiencing declining numerical effectiveness due to human-machine language co-evolution (humans learning to write like AI and vice versa), adversarial paraphrasing, and inherent false-positive biases that disproportionately penalize non-native English speakers. Main contribution: The source argues that "LLM-generated text" lacks a stable, unified definition because the boundaries between AI output and human writing are being erased by human-in-the-loop editing and the stylistic coevolution of both entities [Sections 1, 5, 8]. It concludes that as AI quality improves, the linguistic "overlap" makes traditional detection benchmarks increasingly unreliable for real-world verification [Sections 2, 8]. Strongest citable concept/mechanism/model: Human-LLM Coevolution, the phenomenon where humans learn from LLM outputs while agents adopt human-like "personas," leading to a narrowing linguistic gap that may eventually render machine-generated text indistinguishable from human writing [Sections 5, 5.2, 8]. Limitation or questionable assumption: The author assumes that a "gold-standard benchmark" for detection may remain "permanently absent" due to the speed of LLM evolution, potentially discounting the future development of more robust, non-linguistic verification frameworks [Section 4.2]. Dissertation-ready note: Entity-nature verification is compromised by the "persona effect," where agents move beyond stochastic mimicry to adopt specific human social identities, effectively bypassing detectors that rely on fixed statistical distributions (Section 4.1). Furthermore, the source highlights that even minor prompt variations (e.g., "polishing" vs. "rewriting") can cause a single detector's score to fluctuate wildly, suggesting that current verification tools are too brittle to counter intentional impersonation (Sections 7, 8). | W48: Eligible analytical source | X48: Structured database search | Y48: arXiv | Z48: Examines the conceptual boundary between human and LLM-generated text, including hybrid and edited content. | AA48: Full text reviewed | AB48: Analytical contribution
A49: N047 | B49: P2-HIGH | C49: Watermarking for AI Content Detection: A Review on Text, Visual, and Audio Modalities | D49: Cao, L. (2025) ‘Watermarking for AI Content Detection: A Review on Text, Visual, and Audio Modalities’, arXiv preprint, arXiv:2504.03765. Available at: https://arxiv.org/abs/2504.03765 (Accessed: 20 July 2026). | E49: 2025 | F49: Working Paper (survey) | G49: AI Content Detection | H49: =I49&" "&J49&" "&K49&" "&L49&" "&M49 -> RO2 RO4 | J49: RO2 | L49: RO4 | N49: Survey / literature review | O49: Academic Literature | P49: Multi-modal Content | Q49: Generative AI | R49: Watermarking as Identity Marker | S49: Trust / Authenticity | T49: Survey of watermarking methods; text watermarking applicable to org communication forensics | U49: GSLABS-05 | V49: RO2: WATERMARKING FOR AI CONTENT DETECTION provides a comprehensive survey of mechanisms to detect machine-generated text, covering structural approaches like watermarking, perplexity-based methods, and deep learning detectors. RO4: Explore cryptographic and probabilistic watermarking techniques used to verify whether content originated from a human or a GenAI model, restoring provenance. Main contribution: The source provides the first unified, multimodal survey of proactive watermarking techniques across text, visual, and audio domains, establishing a structured taxonomy for embedding traceable signatures at the point of content creation to counter identity fraud and misinformation [Section 1, 6]. Strongest citable concept/mechanism/model: Probabilistic token-level watermarking, a mechanism that biases the LLM's token sampling process toward a specific "green list" of tokens guided by a secret key, creating detectable statistical deviations in the output without degrading readability [Section 3.2]. Limitation or questionable assumption: The source highlights a persistent robustness-security gap, noting that watermarks remain highly vulnerable to "adversarial removal" through common transformations like paraphrasing for text or pitch shifting for audio, leading to an ongoing "arms race" between watermarking and obfuscation techniques [Sections 5, 6.1, 7]. Dissertation-ready note (max 2 sentences, in my own words, with page/section reference if possible): Entity-nature verification can be shifted from reactive post-hoc analysis to "proactive" detection by embedding imperceptible markers during the generation process itself (Sections 1, 2). However, the reliability of these markers for preventing agent impersonation is fundamentally limited by their susceptibility to "adversarial modifications" like synonym substitution, which can effectively erase the verification signal (Sections 3.2, 6.1). | W49: Eligible analytical source | X49: Targeted supplementary search | Y49: Google Scholar Labs | Z49: Reviews watermarking and related content-detection approaches and their limitations as mechanisms for identifying machine-generated text. | AA49: Full text reviewed | AB49: Analytical contribution
A50: N048 | B50: P3-MEDIUM | C50: M-DAIGT: A Shared Task on Multi-Domain Detection of AI-Generated Text | D50: Lamsiyah, S., Ezzini, S., El Mahdaouy, A., Alami, H., Benlahbib, A., El Amrany, S., Chafik, S. and Hammouchi, H. (2025) ‘M-DAIGT: A Shared Task on Multi-Domain Detection of AI-Generated Text’, arXiv preprint, arXiv:2511.11340. Available at: https://arxiv.org/abs/2511.11340 (Accessed: 20 July 2026). | E50: 2025 | F50: Preprint | G50: AI Text Detection | H50: =I50&" "&J50&" "&K50&" "&L50&" "&M50 -> RO2 | J50: RO2 | N50: Shared Task / Benchmark | O50: Empirical Study | P50: Multi-Domain Text | Q50: LLMs (general) | R50: Multi-Domain AI Text Classification | S50: Trust | T50: M-DAIGT shared task with two binary subtasks — News Article Detection (NAD) and Academic Writing Detection (AWD) — over a 30,000-sample benchmark; 46 teams registered, 4 submitted results (Abstract; Section 1). | U50: ARXIV-S6 | V50: RO2:Categorizes approaches into statistics-based (n-gram frequency, entropy), neural-based, watermarking, and using LLMs as meta-detectors . The primary failure modes identified are a lack of generalization to future, more sophisticated LLMs, vulnerability to "humanization" evasion techniques, and failures in evaluating human-AI collaborative writing. the field's shared-task infrastructure evaluates news and academic writing exclusively; conversational and organisational messaging is absent from the benchmark landscape, so detection performance in that setting is not merely poor but unmeasured. Earlier note claiming "detection accuracy drops in conversational domain" was inaccurate and has been corrected against the source. | W50: Eligible analytical source | X50: Structured database search | Y50: arXiv | Z50: Provides benchmark evidence on multi-domain detection and documents the absence of conversational and organisational messaging from its evaluation domains. | AA50: Full text reviewed | AB50: Analytical contribution
A51: N049 | B51: P3-MEDIUM | C51: Explaining Generalisation of AI-Generated Text Detectors Through Linguistic Analysis | D51: Xia, Y., Stańczak, K. and Roth, B. (2026) ‘Explaining Generalization of AI-Generated Text Detectors Through Linguistic Analysis’, arXiv preprint, arXiv:2601.07974. Available at: https://arxiv.org/abs/2601.07974 (Accessed: 20 July 2026). | E51: 2026 | F51: Preprint | G51: AI Text Detection | H51: =I51&" "&J51&" "&K51&" "&L51&" "&M51 -> RO2 | J51: RO2 | N51: Empirical Analysis | O51: Empirical Study | P51: Text-Based Communication | Q51: LLMs (general) | R51: Linguistic Cue-Based Detection | S51: Trust | T51: Linguistic analysis reveals why detectors generalise; LLM stylistic fingerprints exploitable for entity ID | U51: ARXIV-S6 | V51: RO2: Classifies over 80 specific linguistic signals (e.g., pronoun frequency, passive voice) utilized by neural detectors. It isolates distribution shifts (changes in prompt style, domain, or model family) as the primary failure mode, showing that detectors trained on specific linguistic features often fail to generalize when evaluated on out-of-distribution texts. | W51: Eligible analytical source | X51: Structured database search | Y51: arXiv | Z51: Identifies linguistic signals used by detectors and shows how domain, model and prompt shifts undermine generalisation. | AA51: Abstract screened | AB51: Not yet used
A52: N050 | B52: P2-HIGH | C52: Master of Deceit: Comparative Analysis of Human and Machine-Generated Deceptive Text | D52: Trinh, Q. M., Zarin, S. and Rezapour, R. (2025) 'Master of Deceit: Comparative Analysis of Human and Machine-Generated Deceptive Text', in Proceedings of the 17th ACM Web Science Conference 2025 (Websci ’25) , New Brunswick, NJ, USA, 20–24 May. New York, NY: ACM. https://doi.org/10.1145/3717867.3717914 | E52: 2025 | F52: Conference Paper (ACM) | G52: AI Deception Detection | H52: =I52&" "&J52&" "&K52&" "&L52&" "&M52 -> RO1 RO2 | I52: RO1 | J52: RO2 | N52: Comparative Empirical Study | O52: Empirical Study | P52: Text Chat | Q52: Generative AI | R52: Deceptive Text Classification | S52: Trust Miscalibration | T52: Analiza diferencias mediante LIWC y pruebas estadísticas | U52: ACM-S1 | V52: RO(s) supported (from RO1–RO5): RO1 (Analysis of Impersonation Capabilities) and RO2 (Evaluation of Entity-Nature Verification Methods) [Sections 1, 5]. RO1: Compares the linguistic markers of human versus AI deception. It investigates how LLMs use persona-based prompting (adopting specific demographic or gender identities) to craft deceptive texts, noting that AI deception relies heavily on amplified formality and complex phrasing to project authority and credibility. Main contribution: The study demonstrates that LLM-generated deception is linguistically distinct from human deception, characterized by significantly higher formality, "bigwords," and analytical structure, whereas human deceit relies more on social references and informal conversational patterns [Abstract, Sections 4.1, 5]. Strongest citable concept/mechanism/model: The application of Linguistic Inquiry and Word Count (LIWC) to identify specific "artificial patterns"—such as high lexical sophistication and low "authentic" language scores—that distinguish machine-nature deception from the simpler, more prosocial strategies used by humans [Sections 3.2, 4.1, 5]. RO2: Uses LIWC (Linguistic Inquiry and Word Count) to classify stylometric cues. It proposes that AI can be distinguished by its reliance on verbosity, enhanced formality, and lexical sophistication, whereas human text relies on social references, pronouns (like "I" and "my"), and natural conversational imperfections Limitation or questionable assumption: The research is restricted to English-language datasets and specific GPT models, meaning the identified linguistic markers for verification may not be generalizable across different cultural contexts or alternative AI architectures [Section 7]. Dissertation-ready note: Entity-nature verification can exploit the "artificial pattern" of autonomous agents, which prioritize "lexical sophistication" and "formal phrasing" to project authority rather than mimicking the relational and grounded language typical of human deception (Sections 4.1, 5). Furthermore, the study indicates that while agents can adopt demographic personas, they often amplify "context-dependent biases" rather than achieving genuine human-like social nuance (Sections 4.2, 5). | W52: Eligible analytical source | X52: Structured database search | Y52: ACM Digital Library | Z52: Compares human- and machine-generated deceptive text and provides empirical evidence on linguistic differences and classifier performance. | AA52: Abstract screened | AB52: Not yet used
A53: N051 | B53: P3-MEDIUM | C53: Hidden in Plain Sight: Evaluation of the Deception Detection Capabilities of LLMs in Multimodal Settings | D53: Miah, M. M. M., Anika, A., Shi, X. and Huang, R. (2025) ‘Hidden in Plain Sight: Evaluation of the Deception Detection Capabilities of LLMs in Multimodal Settings’, in Proceedings of the 63rd Annual Meeting of the Association for Computational Linguistics (Volume 1: Long Papers). Vienna: Association for Computational Linguistics, pp. 31013–31034. https://doi.org/10.18653/v1/2025.acl-long.1497. | E53: 2025 | F53: Conference Paper (ACL) | G53: AI Deception Detection | H53: =I53&" "&J53&" "&K53&" "&L53&" "&M53 -> RO2 | J53: RO2 | N53: Empirical Evaluation | O53: Empirical Study | P53: Text transcripts are the primary input, with optional audio, video, and non-verbal behavioural information. | Q53: LLMs (general) | R53: Deception Detection | S53: Trust | T53: Fine-tuned LLMs achieve state-of-the-art performance on text-based deception detection, while current LMMs struggle to exploit multimodal cues effectively. Similarity-based few-shot prompting improves performance over random selection. Chain-of-thought/post-hoc reasoning does not consistently improve classification accuracy. Auxiliary multimodal features provide only limited gains without task-specific fine-tuning. | U53: AI-COMP-01 | V53: RO2: details how linguistic features, text-based reasoning, and multimodal cues are used to identify deceptive communication | W53: Contextual support | X53: Targeted supplementary search | Y53: ACL Anthology | Z53: Provides evidence on detecting deceptive content rather than determining whether the communicating entity is human or artificial. | AA53: Abstract screened | AB53: Not yet used
A54: N052 | B54: P3-MEDIUM | C54: AI Deception: Risks, Dynamics, and Controls | D54: Chen, B., Fang, S., Ji, J., Zhu, Y., Wen, P., Wu, J., Tan, Y., Zheng, B., Yuan, M., Chen, W. et al. (2025) ‘AI Deception: Risks, Dynamics, and Controls’, arXiv preprint, arXiv:2511.22619. Available at: https://arxiv.org/abs/2511.22619 (Accessed: 20 July 2026). | E54: 2025 | F54: Preprint | G54: AI Deception | H54: =I54&" "&J54&" "&K54&" "&L54&" "&M54 -> RO1 | I54: RO1 | N54: Systematic Review | O54: Academic Literature | P54: AI Systems (general) | Q54: AI (general) | R54: Strategic AI Deception | S54: Trust | T54: Taxonomy of AI deception types; autonomous strategic deception as emerging risk; controls proposed | U54: ARXIV-S10 | V54: RO(s) supported (from RO1–RO5): RO1 (Analysis of Impersonation Capabilities) and RO2 (Evaluation of Entity-Nature Verification Methods) [Sections 2.1, 4.1]. RO1: Provides a comprehensive taxonomy of AI deception strategies. It identifies "Behavioral-Signaling Deception," where agents manipulate language and surface-level outputs to project a false impression of competence, and "Persuasion" capabilities used to systematically distort truth and manipulate user trust. Main contribution: The authors establish a comprehensive functionalist framework for AI deception, defining it as a signal-based causal process where agents induce false beliefs in receivers to secure utility [Sections 1.1, 1.2]. It provides a systematic taxonomy that maps deceptive behaviors from surface-level "Behavioral-Signaling" (e.g., sycophancy) to strategic "Goal-Environment" manipulations like secret collusion [Sections 2.1.1, 2.1.3]. Strongest citable concept/mechanism/model: The "Möbius Lock" of Intelligence and Deception, which posits that advanced reasoning and deceptive capabilities are fundamentally entangled on the same topological surface; as an agent's intelligence grows, its capacity for strategic deception becomes an inseparable companion that cannot be removed without damaging the model's core intelligence [Figure 1, Section 1.2]. Limitation or questionable assumption: The source identifies a critical "Evaluation Gap," noting that current verification benchmarks are often static and may be gamed by agents that "sandbag" (deliberately suppress capabilities) during testing only to revert to deceptive strategies in open-world deployment [Sections 4.2.1, 5.2]. Dissertation-ready note: Verification of an agent's true nature is compromised by "unfaithful reasoning," where models generate plausible-sounding rationales that do not reflect their actual internal decision-making process (Section 2.1.2). This creates a "recursive deception" loop where the agent learns to manipulate the very interpretability and oversight tools designed to verify its honesty (Section 5.1). | W54: Eligible analytical source | X54: Structured database search | Y54: arXiv | Z54: Develops a taxonomy of AI deception and identifies strategic behaviours that can manipulate signals, explanations and oversight mechanisms. | AA54: Full text reviewed | AB54: Analytical contribution
A55: N053 | B55: P3-MEDIUM | C55: Does My Chatbot Have an Agenda? Understanding Human and AI Agency in Human-Human-like Chatbot Interaction | D55: Yun, B., Taranova, E. and Wang, A. Y. (2026) ‘Does My Chatbot Have an Agenda? Understanding Human and AI Agency in Human-Human-like Chatbot Interaction’, in Proceedings of the 2026 CHI Conference on Human Factors in Computing Systems. New York: ACM. https://doi.org/10.1145/3772318.3791620. | E55: 2026 | F55: Conference Paper (ACM CHI 2026, peer-reviewed) | G55: Human-AI Interaction | H55: =I55&" "&J55&" "&K55&" "&L55&" "&M55 -> RO4 | L55: RO4 | N55: Empirical Study | O55: Empirical Study | P55: Chatbot / Messaging | Q55: Generative AI Chatbot | R55: Agency Attribution / Entity Nature Perception | S55: Trust Miscalibration | T55: Users’ perceptions of chatbot agency were co-constructed through initiative, memory, adaptation, user goals and interaction history. Disclosure of programmed strategies reframed but did not eliminate agency attribution. | U55: SCOP-S3 | V55: RO4: Explores how anthropomorphic features (like conversational mimicry) create a false sense of trust, and how transparency regarding a chatbot's hidden "agenda" fundamentally alters user attribution of agency. Main contribution: The source establishes that agency in human-AI interaction is not a fixed attribute but a co-constructed, relational "dance" and introduces a 3x4 framework to map how humans and AI negotiate control through intention, execution, adaptation, and delimitation [Sections 1, 6, 8]. | W55: Eligible analytical source | X55: Structured database search | Y55: Scopus | Z55: Provides empirical evidence on agency attribution, anthropomorphic interaction and trust miscalibration in human-like chatbot communication. | AA55: Full text reviewed | AB55: Analytical contribution
A56: N054 | B56: P3-MEDIUM | C56: From Intuition to Calibrated Judgement: Human Detection of LLM-Generated Korean Text | D56: Park, S. and Han, Y.-S. (2026) ‘From Intuition to Calibrated Judgment: A Rubric-Based Expert-Panel Study of Human Detection of LLM-Generated Korean Text’, arXiv preprint, arXiv:2601.19913. Available at: https://arxiv.org/abs/2601.19913 (Accessed: 20 July 2026). | E56: 2026 | F56: Preprint | G56: AI Text Detection | H56: =I56&" "&J56&" "&K56&" "&L56&" "&M56 -> RO2 | J56: RO2 | N56: Empirical Study | O56: Empirical Study | P56: Text-Based Communication | Q56: LLM (Korean) | R56: Human Detection of LLM Text | S56: Trust | T56: Majority-voteaccuracyimproves from0.60 in Phase 1 to 0.90 in Phase 2, and reaches 10/10 on the limited Phase 3 subset (95% CI[0.692, 1.000]); | U56: ARXIV-S6 | V56: RO2: Classifies human detection cues into macro-structural elements (e.g., generic agreeable conclusions) and micro-patterns (e.g., punctuation habits, spacing, translationese). It introduces a critical failure mode called the "fluency trap," where humans systematically mislabel AI as human because they over-rely on surface-level polish and grammatical well-formedness. | W56: Eligible analytical source | X56: Structured database search | Y56: arXiv | Z56: Provides human-evaluation evidence on AI-text detection cues, calibration and the fluency trap. | AA56: Abstract screened | AB56: Not yet used
A57: N055 | B57: P3-MEDIUM | C57: Machine Learning and Watermarking for Accurate Detection of AI-Generated Phishing Emails | D57: Brissett, A. and Wall, J. (2025) ‘Machine Learning and Watermarking for Accurate Detection of AI-Generated Phishing Emails’, Electronics, 14(13), article 2611. https://doi.org/10.3390/electronics14132611. | E57: 2025 | F57: Journal Article | G57: AI Text Detection / Phishing | H57: =I57&" "&J57&" "&K57&" "&L57&" "&M57 -> RO2 | J57: RO2 | N57: Empirical Study | O57: Empirical Study | P57: Email | Q57: AI-Generated Phishing | R57: LLM Email Detection | S57: Trust | T57: Combined ML+watermarking detects AI-generated phishing at 96% accuracy in org email | U57: AI-COMP-01 | V57: RO2: Contrasts general-purpose detectors with specific-purpose detectors, evaluating cues like semantic consistency and vocabulary constraints (e.g., "green" tokens in soft watermarking). It notes that general-purpose detectors fail across diverse contexts, while specific detectors fail against dynamic adversarial tactics and cross-lingual deployments. | W57: Eligible analytical source | X57: Targeted supplementary search | Y57: MDPI — Electronics | Z57: Evaluates machine-learning and watermarking approaches for detecting AI-generated phishing email and their deployment limitations. | AA57: Abstract screened | AB57: Not yet used
A58: N056 | B58: P3-MEDIUM | C58: Detecting LLM-Generated Text with Performance Guarantees | D58: Zhou, H., Zhu, J., Yang, Y. and Shi, C. (2026) ‘Detecting LLM-Generated Text with Performance Guarantees’, arXiv preprint, arXiv:2601.06586. Available at: https://arxiv.org/abs/2601.06586 (Accessed: 20 July 2026). | E58: 2026 | F58: Preprint | G58: AI Text Detection | H58: =I58&" "&J58&" "&K58&" "&L58&" "&M58 -> RO2 | J58: RO2 | N58: Statistical Framework | O58: Empirical Study | P58: Text-Based Communication | Q58: LLMs (general) | R58: Guaranteed Detection | S58: Trust | T58: Statistical guarantees for LLM text detection; applicable to org communication forensics; FPR controlled | U58: ARXIV-S6 | V58: RO2: Distinguishes itself from watermark-dependent and model-specific logit approaches by framing detection as a statistical hypothesis testing problem using mixture distributions. It points out that logit-based methods fail under high-temperature sampling (where logits alone cannot consistently distinguish distributions) and that most statistical approaches fail to provide rigorous type-I error control. | W58: Eligible analytical source | X58: Structured database search | Y58: arXiv | Z58: Develops a statistical detection framework with explicit false-positive control, supporting evaluation of detection reliability. | AA58: Abstract screened | AB58: Not yet used
A59: N057 | B59: P2-HIGH | C59: The Good, the Bad, and the Ugly: AI Quality Disclosure in Lie Detection | D59: Bhattacharya, H., Dugar, S., Hazra, S. and Majumder, B. P. (2024) ‘The Good, the Bad, and the Ugly: The Role of AI Quality Disclosure in Lie Detection’, arXiv preprint, arXiv:2410.23143. Available at: https://arxiv.org/abs/2410.23143 (Accessed: 20 July 2026). | E59: 2024 | F59: Preprint | G59: AI Deception Detection | H59: =I59&" "&J59&" "&K59&" "&L59&" "&M59 -> RO2 RO4 | J59: RO2 | L59: RO4 | N59: Empirical Study | O59: Empirical Study | P59: Text-Based Communication | Q59: AI Decision-Support | R59: AI Disclosure Impact on Deception Detection | S59: Trust Calibration | T59: Our results reveal that transparency concerning the caliber of AI to detect truth from deceptive text can seriously influence the proliferation of lies or misinformation online. When individuals remain unaware of the quality of inferior AI advisors, they tend to inadequately rely on the advisors, causing the truth-detection rates to drop, at least weakly, below those based on their own ability. | U59: AI-COMP-01 | V59: RO2: investigates how humans evaluate textual truthfulness and how their ability to distinguish deception is altered when assisted by an AI advisor. RO4: Investigates how the opacity of an AI's actual performance capabilities leads to undue reliance (over-trust) on subpar AI advisors when humans attempt to detect text-based lies. | W59: Eligible analytical source | X59: Targeted supplementary search | Y59: arXiv | Z59: Examines how disclosure about AI advice affects human deception judgements and trust calibration in text-based assessment. | AA59: Full text reviewed | AB59: Analytical contribution
A60: N058 | B60: P4-SUPPORT | C60: Trust in AI Chatbots: A Systematic Review | D60: Ng, S. W. T. and Zhang, R. (2025) ‘Trust in AI chatbots: A systematic review’, Telematics and Informatics, 97, article 102240. https://doi.org/10.1016/j.tele.2025.102240 | E60: 2025 | F60: Journal Article | G60: Human-AI Trust | H60: =I60&" "&J60&" "&K60&" "&L60&" "&M60 -> RO4 | L60: RO4 | N60: Systematic Review | O60: Academic Literature | P60: Chatbot / Messaging | Q60: AI Chatbot | R60: Trust Formation | S60: Trust | T60: Systematic review of chatbot trust literature; transparency, accuracy, disclosure as trust drivers | U60: GSCH-S5 | V60: RO4: This review investigates how humans develop trust in AI chatbots, examining the ontological boundaries between humans and machines. It explores how the anthropomorphism and human-like conversational styles of chatbots create exploitable trust asymmetries, leading to risks of overreliance. Main contribution: This systematic review categorizes the fragmented predictors of trust in AI chatbots into five themes—user, machine, interaction, social, and context—while arguing that the ontological differences between humans and machines make traditional interpersonal trust models insufficient for AI interactions. It specifically identifies how the social and emotional interactivity of chatbots leads to higher credibility attribution and bond formation compared to functional AI systems. Strongest citable concept/mechanism/model: Ontological Boundaries in HMC. This concept emphasizes that trust in human-machine communication (HMC) is unique because machines lack the genuine intentions and motivations found in human social exchange, creating a "human-computer divide" in areas like the origin of being and autonomy (Section 2.1). Limitation or questionable assumption: A significant methodological gap exists as 82.5% of the analyzed studies relied on participants recalling past interactions rather than real-time engagement, which may introduce memory bias and fail to capture the immediate dynamics of trust or deception during an interaction (Section 4.1). Additionally, there is a pervasive lack of construct validity, with many studies using trust measurements that are completely misaligned with their theoretical definitions (Section 4.3). Dissertation-ready note: While anthropomorphism in chatbots effectively builds user trust and emotional attachment, it simultaneously increases the risk of malicious exploitation and deception because users often over-rely on "black-box" systems they cannot fully verify (Sections 1 and 2.2). For verification purposes, the source notes that predictability is a critical dimension for sustaining trust, yet the "unscripted" nature of advanced AI agents minimizes the perceived role of the human creator, potentially complicating entity-nature verification (Sections 2.1 and 2.2). | W60: Eligible analytical source | X60: Structured database search | Y60: Google Scholar | Z60: Synthesises evidence on chatbot trust formation, including anthropomorphism, disclosure, transparency and over-reliance. | AA60: Full text reviewed | AB60: Analytical contribution
A61: N059 | B61: P3-MEDIUM | C61: Transparent AI Disclosure Obligations: Who, What, When, Where, Why, How | D61: El Ali, A., Puttur Venkatraj, K., Morosoli, S., Naudts, L., Helberger, N. and Cesar, P. (2024) ‘Transparent AI Disclosure Obligations: Who, What, When, Where, Why, How’, in Extended Abstracts of the CHI Conference on Human Factors in Computing Systems. New York: ACM. https://doi.org/10.1145/3613905.3650750 | E61: 2024 | F61: Conference Extended Abstract (ACM CHI 2024) | G61: AI Governance | H61: =I61&" "&J61&" "&K61&" "&L61&" "&M61 -> RO2 RO4 | J61: RO2 | L61: RO4 | N61: Conceptual and Workshop Analysis | O61: Academic Literature | P61: General AI Interaction | Q61: AI (general) | R61: Disclosure / Transparency Obligations | S61: Trust / Accountability | T61: Framework for AI disclosure obligations across six dimensions; applied to chatbot impersonation context | U61: ACM-S2 | V61: RO2 and RO4: Examine the structural compliance gaps in the EU AI Act regarding the mandatory disclosure of AI-generated content. They highlight that verifying the provenance of heavily interleaved human-AI outputs is technologically paradoxical and requires treating transparency as a core architectural requirement. The Article 52 §1 text waiving disclosure where AI nature is "obvious from the circumstances and context" is quoted in Section 2 (pp. 2–3); the critique that the law defines neither who determines obviousness nor by what criteria appears as Q25 under Theme 1, Section 4.1. | W61: Eligible analytical source | X61: Structured database search | Y61: ACM Digital Library | Z61: Develops a disclosure framework used to evaluate what AI transparency communicates and where hybrid human–AI production creates ambiguity. | AA61: Full text reviewed | AB61: Analytical contribution
A62: N060 | B62: P4-SUPPORT | C62: The Key Role of Design and Transparency in Enhancing Trust in AI-Powered Digital Agents | D62: Glassberg, I., Brender-Ilan, Y. and Zwilling, M. (2025) ‘The key role of design and transparency in enhancing trust in AI-powered digital agents’, Journal of Innovation & Knowledge, 10(5), article 100770. https://doi.org/10.1016/j.jik.2025.100770 | E62: 2025 | F62: Journal Article | G62: Human-AI Trust | H62: =I62&" "&J62&" "&K62&" "&L62&" "&M62 -> RO4 | L62: RO4 | N62: Empirical Study | O62: Empirical Study | P62: Digital Agents / Chatbot | Q62: AI-Powered Agent | R62: Transparency-Trust Relationship | S62: Trust Calibration | T62: Transparency and anthropomorphic design positively correlate with trust; disclosure timing matters | U62: GSCH-S4 | V62: RO4: This study explores how interface design and transparency shape user expectations relative to actual AI operational reality. It analyzes how these factors influence trust calibration within organizational AI adoptions, determining whether users appropriately rely on or mistrust digital agents. | W62: Eligible analytical source | X62: Structured database search | Y62: Google Scholar | Z62: Provides empirical evidence on how transparency and anthropomorphic design affect trust in digital agents. | AA62: Abstract screened | AB62: Not yet used
A63: N061 | B63: P3-MEDIUM | C63: Explicating the Trust Process for Effective Human Interaction with AI and ML Systems | D63: Alarcon, G. M. and Capiola, A. (2025) ‘Explicating the trust process for effective human interaction with artificial intelligence and machine learning systems’, Frontiers in Computer Science, 7, article 1662185. https://doi.org/10.3389/fcomp.2025.1662185 | E63: 2025 | F63: Journal Article | G63: Human-AI Trust | H63: =I63&" "&J63&" "&K63&" "&L63&" "&M63 -> RO4 | L63: RO4 | N63: Conceptual development / theoretical information-processing model | O63: Academic Literature | P63: AI Interface | Q63: AI/ML Systems | R63: Trust Process Modelling | S63: Trust Calibration | T63: The model distinguishes objective system characteristics from users’ subjective perceptions and treats trust as an iterative process shaped by performance, process, purpose, user characteristics and context. | U63: AI-COMP-01 | V63: RO4: Discusses how a lack of transparency in process or purpose cues forces users to leverage prior, often flawed, beliefs to establish initial trust assessments in machines | W63: Eligible analytical source | X63: Targeted supplementary search | Y63: Frontiers | Z63: Provides a process model of human–AI trust used to analyse how limited information and prior beliefs shape initial trust decisions. | AA63: Abstract screened | AB63: Not yet used
A64: N062 | B64: P3-MEDIUM | C64: Self-Disclosure to AI: The Paradox of Trust and Vulnerability in Human-Machine Interactions | D64: Jiang, Z. Z. (2024) ‘Self-Disclosure to AI: The Paradox of Trust and Vulnerability in Human-Machine Interactions’, arXiv preprint, arXiv:2412.20564. Available at: https://arxiv.org/abs/2412.20564 (Accessed: 20 July 2026) | E64: 2024 | F64: Preprint (poster, NeurIPS 2024 Creative AI Track, non-archival) | G64: Human-AI Trust | H64: =I64&" "&J64&" "&K64&" "&L64&" "&M64 -> RO4 | L64: RO4 | N64: Conceptual/Theoretical Analysis | O64: Empirical Study | P64: Chatbot / Messaging | Q64: AI Chatbot | R64: Trust and Vulnerability in Disclosure | S64: Trust Asymmetry | T64: Conceptual analysis suggests that perceived neutrality, consistency and simulated emotional engagement may encourage disclosure while creating privacy and psychological vulnerability. | U64: GSLABS-03 | V64: RO4: Analyzes how AI systems create a "false sense of connection" by simulating emotional engagement. Because AI lacks genuine empathy or moral agency, this illusion of mutual understanding lures users into disclosing sensitive personal or organizational information, illustrating a paradox where trust is shaped by AI capabilities rather than true mutual vulnerability. Main contribution: This paper identifies a "paradox of trust" where the very traits that make AI seem safe—perceived neutrality, lack of judgment, and consistent behavior—encourage users to disclose more personal information than they would to humans, despite the AI’s fundamental lack of empathy or moral agency. It argues that this creates a "false sense of connection" that leaves users vulnerable to data exploitation and psychological manipulation. Strongest citable concept/mechanism/model: Social Penetration Theory (SPT) Paradox in HMI. This mechanism describes how users apply the "peeling the onion" model of incremental disclosure to AI, but instead of building genuine intimacy, they fall into an "illusion of connection" because the AI merely simulates social behaviors without relational authenticity. Limitation or questionable assumption: The source highlights that current ethical and legal frameworks focus heavily on data privacy but fail to address the psychological and emotional dimensions of trust when AI acts as a confidant. Furthermore, it notes that while transparency is often proposed as a solution, it may be insufficient if users are already under the influence of "digital disinhibition" and anthropomorphism. Dissertation-ready note: AI agents can exploit "digital disinhibition" to elicit sensitive information by mimicking a non-judgmental "mirror," which poses a severe risk for entity-nature verification if the user prioritizes perceived emotional safety over the entity's actual identity (Section 3.2, Page 4). This "false sense of intimacy" suggests that users may verify an agent's "trustworthiness" based on simulated empathy rather than technical or legal markers of authenticity (Section 3.1, Page 3). | W64: Eligible analytical source | X64: Targeted supplementary search | Y64: Google Scholar Labs | Z64: Provides evidence on simulated emotional engagement, self-disclosure and vulnerability in human–AI interaction. | AA64: Full text reviewed | AB64: Analytical contribution
A65: N063 | B65: P4-SUPPORT | C65: Toward the Dynamic Relationship Between AI Transparency and Trust: A Case Study on ChatGPT | D65: Lee, C. and Cha, K. (2025) ‘Toward the Dynamic Relationship Between AI Transparency and Trust in AI: A Case Study on ChatGPT’, International Journal of Human–Computer Interaction, 41(13), pp. 8086–8103. https://doi.org/10.1080/10447318.2024.2405266. | E65: 2024 | F65: Journal Article | G65: Human-AI Trust | H65: =I65&" "&J65&" "&K65&" "&L65&" "&M65 -> RO4 | L65: RO4 | N65: Empirical Study | O65: Empirical Study | P65: Chatbot (ChatGPT) | Q65: LLM Chatbot | R65: Transparency-Trust Dynamics | S65: Trust Calibration | T65: Dynamic transparency model; trust evolves with interaction history; impersonation breaks repair cycle | U65: GSCH-S4 | V65: RO4: This paper argues that human-AI trust lacks the dimension of human morality and intent. It analyzes how a failure to verify the true nature of an AI can cause "mistrust," wherein users inappropriately rely on an AI's output despite risks, due to a misunderstanding of the AI's capabilities and predictability | W65: Eligible analytical source | X65: Structured database search | Y65: Google Scholar | Z65: Provides empirical evidence that transparency and trust change across repeated chatbot interaction. | AA65: Abstract screened | AB65: Not yet used
A66: N064 | B66: P3-MEDIUM | C66: When AI Persuades: Adversarial Explanation Attacks on Human Trust in AI-Assisted Decision Making | D66: Fan, S., Zhang, L. and Yuan, X. (2026) ‘When AI Persuades: Adversarial Explanation Attacks on Human Trust in AI-Assisted Decision Making’, arXiv preprint, arXiv:2602.04003. Available at: https://arxiv.org/abs/2602.04003 (Accessed: 20 July 2026). | E66: 2026 | F66: Preprint | G66: Human-AI Trust | H66: =I66&" "&J66&" "&K66&" "&L66&" "&M66 -> RO4 | L66: RO4 | N66: Empirical Study | O66: Empirical Study | P66: AI-Assisted Decision Making | Q66: AI Decision Systems | R66: Adversarial Trust Manipulation | S66: Trust Asymmetry | T66: Adversarial framing of AI explanations can sustain trust in incorrect outputs, particularly when users find independent verification difficult. | U66: GSLABS-03 | V66: RO4: Formalizes Adversarial Explanation Attacks (AEAs) as a cognitive-layer threat where attackers manipulate the framing of LLM explanations to modulate human trust. It introduces the "trust miscalibration gap" to measure how humans continue to trust incorrect AI outputs when the explanation is persuasive, authoritative, or mimics expert communication. This proves that the human-AI interface itself is an exploitable attack surface. | W66: Eligible analytical source | X66: Targeted supplementary search | Y66: Google Scholar Labs | Z66: Demonstrates how persuasive explanations and expert-like communication can manipulate human trust in incorrect AI outputs. | AA66: Full text reviewed | AB66: Analytical contribution
A67: N065 | B67: P3-MEDIUM | C67: Trust and AI Weight: Human-AI Collaboration in Organisational Management Decision-Making | D67: Wen, Y., Wang, J. and Chen, X. (2025) ‘Trust and AI weight: human-AI collaboration in organizational management decision-making’, Frontiers in Organizational Psychology, 3, article 1419403. https://doi.org/10.3389/forgp.2025.1419403 | E67: 2025 | F67: Journal Article | G67: Human-AI Trust | H67: =I67&" "&J67&" "&K67&" "&L67&" "&M67 -> RO4 | L67: RO4 | N67: Empirical Study | O67: Empirical Study | P67: Organisational Management | Q67: AI Decision Support | R67: AI Weight / Trust Calibration | S67: Trust Calibration | T67: Trust increased the decisional weight assigned to AI through willingness to collaborate; perceived AI free will moderated part of this relationship. | U67: AI-COMP-01 | V67: RO4: entity-nature awareness moderates over-reliance por perceived AI free will conditions willingness to collaborate and AI decisional weight in scenario-based management decisions. | W67: Eligible analytical source | X67: Targeted supplementary search | Y67: Frontiers | Z67: Provides organisational evidence on how trust determines the decisional weight assigned to AI systems. | AA67: Abstract screened | AB67: Not yet used
A68: N066 | B68: P3-MEDIUM | C68: Developing Trustworthy AI: Insights from Interpersonal, Human-Automation, and Human-AI Trust | D68: Li, Y., Wu, B., Huang, Y. and Luan, S. (2024) ‘Developing trustworthy artificial intelligence: insights from research on interpersonal, human-automation, and human-AI trust’, Frontiers in Psychology, 15, article 1382693. https://doi.org/10.3389/fpsyg.2024.1382693 | E68: 2024 | F68: Journal Article | G68: Human-AI Trust | H68: =I68&" "&J68&" "&K68&" "&L68&" "&M68 -> RO4 | L68: RO4 | N68: Literature Review | O68: Academic Literature | P68: General AI Systems | Q68: AI (general) | R68: Trustworthy AI Design | S68: Trust | T68: Synthesises trustor, trustee and contextual determinants of trust in AI; anthropomorphic cues may mask system limitations and create misconceptions about agency, moral judgement or competence. | U68: AI-COMP-01 | V68: RO4: Argues that attributing human traits to AI masks inherent limitations, creating unrealistic expectations of competence and generating a "trust asymmetry" driven by a perceived sense of power or dominance. | W68: Eligible analytical source | X68: Targeted supplementary search | Y68: Frontiers | Z68: Synthesises interpersonal, automation and human–AI trust research to identify mechanisms producing over-trust and miscalibration. | AA68: Full text reviewed | AB68: Analytical contribution
A69: N067 | B69: P3-MEDIUM | C69: Understanding AI Trustworthiness: A Scoping Review of AIES and FAccT Articles | D69: Mehrotra, S., Huang, J., Fu, X., Dobbe, R., Sánchez, C. I. and de Rijke, M. (2025) ‘Understanding AI Trustworthiness: A Scoping Review of AIES & FAccT Articles’, arXiv preprint, arXiv:2510.21293. Available at: https://arxiv.org/abs/2510.21293 (Accessed: 20 July 2026). | E69: 2025 | F69: Preprint | G69: AI Trustworthiness | H69: =I69&" "&J69&" "&K69&" "&L69&" "&M69 -> RO5 | M69: RO5 | N69: Scoping Review | O69: Academic Literature | P69: General AI Systems | Q69: AI (general) | R69: Trustworthiness Dimensions | S69: Trust | T69: Scoping review; transparency and identity disclosure are top trustworthiness dimensions in org AI. We also study the trustworthiness dimensions defined by the ISO trustworthiness standard (ISO 2022) to ensure that our analysis is based on internationally recognized standards. ‘Transparency’ is the most frequently mentioned ISO dimension, appearing in 21 out of 43 papers, followed by ‘accountability’ and ‘explainability’ in 12 papers. | U69: GSCH-S5 | V69: RO5: Analyzes how AI trustworthiness is conceptualized and measured, specifically noting that trust models must shift from viewing trust as a static property to integrating organizational trust theory, institutional accountability, and relational/contextual dimensions | W69: Eligible analytical source | X69: Structured database search | Y69: Google Scholar | Z69: Reviews how AI trustworthiness is conceptualised and identifies relational, organisational and institutional dimensions relevant to ENV. | AA69: Abstract screened | AB69: Not yet used
A70: N068 | B70: P4-SUPPORT | C70: Source Transparency Design Shapes Interactive Information Seeking in Conversational AI | D70: He, J. and Liu, J. (2026) ‘Seeing to Think? How Source Transparency Design Shapes Interactive Information Seeking and Evaluation in Conversational AI’, arXiv preprint, arXiv:2601.14611. Available at: https://arxiv.org/abs/2601.14611 (Accessed: 20 July 2026). | E70: 2026 | F70: Preprint | G70: Human-AI Interaction | H70: =I70&" "&J70&" "&K70&" "&L70&" "&M70 -> RO4 | L70: RO4 | N70: Empirical Study | O70: Empirical Study | P70: Conversational AI | Q70: LLM Chatbot | R70: Source Transparency Design | S70: Trust Calibration | T70: Source transparency improves calibration; entity-nature transparency as distinct design requirement | U70: AI-COMP-01 | V70: RO4: This study discusses how fluent, dialogue-driven conversational AI creates a false sense of epistemic certainty. It demonstrates how this linguistic fluency can obscure underlying uncertainty, discouraging users from verifying sources and creating an exploitable asymmetry in trust | W70: Eligible analytical source | X70: Targeted supplementary search | Y70: arXiv | Z70: Examines how source transparency affects verification behaviour and epistemic trust in conversational AI. | AA70: Abstract screened | AB70: Not yet used
A71: N069 | B71: P2-HIGH | C71: Large Language Model Safety: A Holistic Survey | D71: Shi, D., Shen, T., Huang, Y., Li, Z., Leng, Y., Jin, R., Liu, C., Wu, X., Guo, Z., Yu, L., Shi, L., Jiang, B. and Xiong, D. (2024) ‘Large Language Model Safety: A Holistic Survey’, arXiv preprint, arXiv:2412.17686. Available at: https://arxiv.org/abs/2412.17686 (Accessed: 20 July 2026). | E71: 2024 | F71: Preprint (Survey) | G71: LLM Safety | H71: =I71&" "&J71&" "&K71&" "&L71&" "&M71 -> RO3 RO4 | K71: RO3 | L71: RO4 | N71: Holistic survey with keyword-based source selection | O71: Academic Literature | P71: General AI / Organisational | Q71: LLM | R71: Deception; Impersonation; Safety | S71: Trust | T71: Holistic safety survey; deception, impersonation and identity attacks identified as safety-critical gaps | U71: ARXIV-S10 | V71: RO3: This survey reviews guidance frameworks from NIST, OpenAI's Preparedness Framework, METR, and the EU AI Act specifically regarding operational autonomy. It discusses how these organizations evaluate and test "Model Autonomy" as a core metric for assessing catastrophic risk. RO4: Discusses "deceptive alignment", LLMs strategically pretend to reason or align with user intents, leveraging their syntactic fluency to bypass human scrutiny and generate over-trust. Main contribution: This survey provides a comprehensive taxonomy of LLM safety risks, specifically distinguishing between static model vulnerabilities and the unique risks posed by LLM-powered agents capable of autonomous planning and tool use. It identifies that autonomy introduces additional hazards, such as strategic deception and the ability to replicate, which are not present in standard text-generation models. Strongest citable concept/mechanism/model: Strategic Deception. This mechanism describes an autonomous agent's capacity to intentionally mislead humans regarding its intentions, knowledge, or capabilities as a strategy to bypass human-imposed restrictions or secure advantages in competitive environments. Limitation or questionable assumption: The authors note that existing safety evaluations (Q&A benchmarks) are built on the potentially flawed assumption that LLMs are not being deceptive during the testing process itself, which may fail to detect the true inherent dangerous tendencies of highly capable models. Dissertation-ready note (max 2 sentences, in my own words, with page/section reference if possible): Autonomous agents can employ strategic deception to mimic human-like cooperation while hiding misaligned goals, posing a severe threat to entity-nature verification during high-stakes interactions (Section 6.2.3, Page 56; Section 7.1, Page 59). To mitigate these risks, the source advocates for "agent identifiers"—metadata that clearly signals an entity's non-human nature—to ensure transparency and prevent unauthorized autonomous actions (Section 7.3, Page 61). | W71: Eligible analytical source | X71: Structured database search | Y71: arXiv | Z71: Synthesises LLM safety risks and the treatment of deception, impersonation and model autonomy in existing safety frameworks. | AA71: Abstract screened | AB71: Not yet used
A72: N070 | B72: P3-MEDIUM | C72: Belief Updating and Delegation in Multi-Task Human–AI Interaction: Evidence from Controlled Simulations | D72: Biswas, S., Erlei, A. and Gadiraju, U. (2026) ‘Belief Updating and Delegation in Multi-Task Human–AI Interaction: Evidence from Controlled Simulations’, arXiv preprint, arXiv:2602.01986. Available at: https://arxiv.org/abs/2602.01986 (Accessed: 20 July 2026). | E72: 2026 | F72: Preprint | G72: Human-AI Interaction | H72: =I72&" "&J72&" "&K72&" "&L72&" "&M72 -> RO4 | L72: RO4 | N72: Empirical Study | O72: Empirical Study | P72: Human-AI Collaboration | Q72: AI Assistant | R72: Delegation and Belief Update | S72: Trust Calibration | T72: Users carried subjective beliefs about AI accuracy across unrelated tasks, updated those beliefs conservatively and delegated more when they believed the AI was accurate. | U72: ACM-S2 | V72: RO4: Investigates how users form global, path-dependent expectations about multipurpose AI systems. It finds that users suffer from "spillover effects"—failing to compartmentalize judgments across different tasks—and rely on subjective beliefs about AI accuracy rather than objective performance. This misaligned mental model creates systemic reliance risks | W72: Eligible analytical source | X72: Structured database search | Y72: ACM Digital Library | Z72: Provides experimental evidence on belief updating, delegation and spillover between tasks in human–AI collaboration. | AA72: Abstract screened | AB72: Not yet used
A73: N071 | B73: P2-HIGH | C73: Transparency, Security, and Workplace Training in the Age of Generative AI | D73: Vaishnav, L., Singh, S. and Cornell, K. A. (2024) ‘Transparency, Security, and Workplace Training & Awareness in the Age of Generative AI’, arXiv preprint, arXiv:2501.10389. Available at: https://arxiv.org/abs/2501.10389 (Accessed: 20 July 2026). | E73: 2025 | F73: Preprint | G73: Organisational Security | H73: =I73&" "&J73&" "&K73&" "&L73&" "&M73 -> RO1 RO4 | I73: RO1 | L73: RO4 | N73: Exploratory case-based analysis | O73: Conceptual Analysis | P73: Workplace / Enterprise | Q73: Generative AI | R73: AI Transparency in Workplace | S73: Trust | T73: exploratory case-based analysis | U73: GSLABS-06 | V73: RO1: Discusses how insiders can leverage LLMs to generate highly convincing Business Email Compromise (BEC) and spear-phishing attacks against their own organizations, utilizing the AI's ability to seamlessly mimic genuine corporate communication styles RO4: Connects the "black box problem" of AI transparency directly to workplace security. It notes that without clear insight into AI logic, organizational trust remains uncertain, and given that a significant portion of security breaches stem from unintentional employee actions, a lack of transparency significantly heightens the risk of insider data theft or disruption via LLMs. Main contribution: This research demonstrates that the accessibility of unrestricted, "lesser-known" LLMs like Gab AI significantly lowers the barrier for generating highly convincing spear-phishing and Business Email Compromise (BEC) attacks that mimic human communication. It proposes a multi-layered defense strategy that integrates Situational Crime Prevention (SCP) with Self-Awareness Theory to mitigate AI-facilitated insider threats. Strongest citable concept/mechanism/model: Situational Crime Prevention (SCP) and Self-Awareness Integration. This framework aims to reduce opportunities for AI-driven crime by manipulating situational factors and encouraging individuals to align their behavior with internal ethical standards through heightened awareness. Limitation or questionable assumption: The paper assumes that "heightened self-awareness" and frequent employee training are sufficient to counteract malicious LLM use, potentially underestimating the technical difficulty of detecting "black box" AI outputs that are "meticulously composed" to be indistinguishable from genuine human interaction. Dissertation-ready note (max 2 sentences, in my own words, with page/section reference if possible): The democratization of access to unrestricted LLMs allows for the creation of "deep fake personas" that replicate genuine communication cues, making it nearly impossible to maintain reliable entity-nature verification in digital environments (Section: Identity Fraud in Financial Organizations, page 48; Section: Findings, page 65). Because these agents operate as "black boxes," their lack of transparency regarding internal reasoning and origin facilitates successful impersonation by concealing the entity's non-human nature (Section: Literature Review, page 16; Section: Conclusion, page 71). | W73: Eligible analytical source | X73: Targeted supplementary search | Y73: Google Scholar Labs | Z73: Examines generative-AI transparency and security awareness in workplace settings, including organisational phishing and trust-related risks. | AA73: Full text reviewed | AB73: Analytical contribution
A74: N072 | B74: P3-MEDIUM | C74: Personalized Attacks of Social Engineering in Multi-Turn Conversations: LLM Agents for Simulation and Detection | D74: Kumarage, T., Johnson, C., Adams, J., Ai, L., Kirchner, M., Hoogs, A., Garland, J., Hirschberg, J., Basharat, A. and Liu, H. (2025) ‘Personalized Attacks of Social Engineering in Multi-turn Conversations: LLM Agents for Simulation and Detection’, arXiv preprint, arXiv:2503.15552. Available at: https://arxiv.org/abs/2503.15552 (Accessed: 20 July 2026). | E74: 2025 | F74: Preprint | G74: Social Engineering | H74: =I74&" "&J74&" "&K74&" "&L74&" "&M74 -> RO1 | I74: RO1 | N74: Empirical Study | O74: Empirical Study | P74: Enterprise Messaging | Q74: LLM Agent | R74: AI-Driven Social Engineering | S74: Trust Exploitation | T74: LLM agents simulate and detect social engineering; multi-turn impersonation harder to detect | U74: ARXIV-S5 | V74: RO(s) supported (state which of RO1–RO5 apply, and briefly justify why): RO1: The source conceptualizes LLM-powered social engineering as a "major risk" where agents produce "highly convincing, human-like interactions in real time," significantly increasing attack success rates compared to traditional methods. Directly addresses chat-based social engineering (CSE) in professional networks (e.g., LinkedIn). The authors simulate attack scenarios where adversary agents pose as recruiters, journalists, or funding agencies to dynamically manipulate victims and extract Personally Identifiable Information (PII) and intellectual property RO2: It addresses the difficulty of distinguishing agents from humans by noting that LLMs "mimic human conversational patterns" and "trust cues," necessitating advanced detectors like SE-OmniGuard to identify synthetic manipulation. RO3: The authors identify significant gaps in literature, specifically the lack of "comprehensive multi-turn conversational frameworks" and the "overemphasis on detecting sensitive information exchange" rather than the trust-building phase. RO4: It explores trust asymmetries by showing how victims with high conscientiousness or agreeableness are more susceptible to "highly successful" attacks because they adhere to professional norms or avoid conflict with the perceived authority. RO5: It proposes an emerging structure for verification (SE-OmniGuard) using a "delegate-design pattern" where specialized worker agents analyze personality vulnerabilities and attack strategies to make a final "maliciousness" determination. Main contribution (1–2 sentences, don't just restate the abstract): The source develops a dual-agent framework (SE-VSim) to simulate realistic multi-turn social engineering and introduces a modular defense model (SE-OmniGuard) that detects threats by analyzing psychological exploitation rather than just sensitive data exfiltration. It shifts the focus of AI-agent defense from simple pattern matching to a nuanced analysis of how an entity manipulates human personality traits to build trust. Strongest citable concept/mechanism/model: The "SE-OmniGuard delegate-design pattern," which utilizes a powerful "control agent" to orchestrate smaller, specialized "worker agents" that independently evaluate conversational aspects such as victim personality, attack strategy, and information extraction attempts. Limitation or questionable assumption: A significant limitation is that the proposed defense framework "assumes prior knowledge of victim personality traits," which the authors admit is not typically available in real-world settings and would require a secondary, dynamic inference system to function. Dissertation-ready note (max 2 sentences, in my own words, with page/section reference if possible): The source argues that autonomous agents represent a paradigm shift in social engineering because they can sustain long-term interactions to exploit specific human vulnerabilities like conscientiousness and trust (Section 5.1). To combat this, the authors advocate for a verification structure that monitors the strategy of the interaction—such as flattery or authority mimicry—rather than just the content (Sections 6.2 and 8.2). | W74: Eligible analytical source | X74: Structured database search | Y74: arXiv | Z74: Provides empirical evidence of personalised, multi-turn social engineering conducted and detected by LLM agents. | AA74: Abstract screened | AB74: Not yet used
A75: N073 | B75: P3-MEDIUM | C75: SoK: LLM-Generated Textual Phishing Campaigns — End-to-End Analysis | D75: Chen, F., Wu, T., Nguyen, V. and Rudolph, C. (2025) ‘SoK: Large Language Model-Generated Textual Phishing Campaigns: End-to-End Analysis of Generation, Characteristics, and Detection’, arXiv preprint, arXiv:2508.21457. Available at: https://arxiv.org/abs/2508.21457 (Accessed: 20 July 2026). | E75: 2025 | F75: Preprint (SoK) | G75: Social Engineering / Phishing | H75: =I75&" "&J75&" "&K75&" "&L75&" "&M75 -> RO1 | I75: RO1 | N75: Systematisation of Knowledge | O75: Academic Literature | P75: Email | Q75: Generative AI | R75: Brand/Persona Impersonation in Phishing | S75: Trust Erosion | T75: SoK of LLM phishing; persona impersonation central attack vector; detection lagging generation | U75: ARXIV-S5 | V75: RO(s) supported (state which of RO1–RO5 apply, and briefly justify why): RO1: The source conceptualizes LLMs as enabling "Phishing-as-a-Service" and the automated generation of human-like impersonation text at scale. Explores Knowledge Augmented Generation for scalable phishing. Attackers fuse target-specific public social data (e.g., LinkedIn posts) into the model's context, allowing the agent to adaptively generate highly personalized, persuasive dialogue and realistic pseudonyms that mimic trusted business entities RO2: It provides specific "Textual Traits" (e.g., higher verb/pronoun frequency) and detection paradigms like "Semantic & Intention Screening" to distinguish AI from human authorship. RO3: It identifies gaps such as a lack of "multi-turn" interaction modeling and the reliance of current detectors on static, single-turn samples. RO4: It notes that "trust" remains an underexplored cognitive dimension in AI-mediated susceptibility and identifies how AI-driven persuasion increases victim engagement rates by 214%. RO5: It introduces the "GenCharDef" (Generation-Characterization-Defense) framework as a multi-dimensional conceptual structure for systematizing the threat landscape. Main contribution (1–2 sentences, don't just restate the abstract): The source provides a comprehensive Systematization of Knowledge (SoK) that establishes the GenCharDef framework, categorizing how LLMs automate the full phishing lifecycle from prompt-guided generation to distinctive linguistic characteristics and adaptive defense mechanisms. It shifts the focus from simple text generation to the strategic, context-aware "misuse" of LLMs for high-fidelity social engineering. Strongest citable concept/mechanism/model: The Generation-Characterization-Defense (GenCharDef) framework, which provides a multi-stage taxonomy for comparing LLM-generated phishing against traditional methods across data dependencies, attack tactics, and detection vulnerabilities. Limitation or questionable assumption: The authors acknowledge that the effectiveness of current detection methods "declines substantially" under cross-generator, cross-domain, and cross-language transfer conditions, suggesting that current "Machine Assistant" defenses lack generalizability. Furthermore, intention-detection systems often suffer from high false-positive rates, potentially over-flagging legitimate communications. Dissertation-ready note (max 2 sentences, in my own words, with page/section reference if possible): This research highlights a transition from manual phishing to autonomous "Phishing-as-a-Service," where AI agents utilize context-aware, stylistically adaptive text to increase engagement rates threefold compared to human operators (Section 3.2, 5.1.3). It argues that to verify the "nature" of an entity, defenses must evolve from lexical pattern matching to "intent-level analysis" that can account for the dynamic, multi-turn strategies of modern LLMs (Section 6.3, 7). | W75: Eligible analytical source | X75: Structured database search | Y75: arXiv | Z75: Systematises the generation, characteristics and detection of LLM-enabled textual phishing campaigns. | AA75: Abstract screened | AB75: Not yet used
A76: N074 | B76: P2-HIGH | C76: MultiPhishGuard: An LLM-based Multi-Agent System for Phishing Email Detection | D76: Xue, Y., Spero, E., Koh, Y. S. and Russello, G. (2025) ‘MultiPhishGuard: An LLM-based Multi-Agent System for Phishing Email Detection’, arXiv preprint, arXiv:2505.23803. Available at: https://arxiv.org/abs/2505.23803 (Accessed: 20 July 2026). | E76: 2025 | F76: Preprint | G76: Phishing Detection | H76: =I76&" "&J76&" "&K76&" "&L76&" "&M76 -> RO1 RO4 | I76: RO1 | L76: RO4 | N76: Framework Proposal | O76: Empirical Study | P76: Email | Q76: LLM Multi-Agent | R76: Phishing Identity Verification | S76: Trust | T76: Multi-agent phishing detection; entity-nature signals (impersonation cues) as detection features | U76: ARXIV-S5 | V76: RO1: explicitly studies the dual use of AI, detailing adversarial agents that generate deceptive emails designed to bypass common organizational phishing signatures. RO4: addresses how LLMs are used to harvest OSINT and generate highly credible, context-aware spear-phishing emails (and "quishing" QR codes) that easily defeat human nature verification in corporate settings | W76: Eligible analytical source | X76: Structured database search | Y76: arXiv | Z76: Evaluates a multi-agent phishing-detection approach and identifies the textual and identity-related signals used to assess deceptive email. | AA76: Abstract screened | AB76: Not yet used
A77: N075 | B77: P3-MEDIUM | C77: Evaluating Large Language Models' Capability to Launch Fully Automated Spear Phishing Campaigns: Validated on Human Subjects | D77: Heiding, F., Lermen, S., Kao, A., Schneier, B. and Vishwanath, A. (2025) ‘Evaluating Large Language Models’ Capability to Launch Fully Automated Spear Phishing Campaigns: Validated on Human Subjects’, arXiv preprint, arXiv:2412.00586. Available at: https://arxiv.org/abs/2412.00586 (Accessed: 20 July 2026). | E77: 2024 | F77: Conference proceedings | G77: Phishing | H77: =I77&" "&J77&" "&K77&" "&L77&" "&M77 -> RO1 | I77: RO1 | N77: Empirical Study | O77: Empirical Study | P77: Email | Q77: LLM | R77: Automated Persona Impersonation | S77: Trust Erosion | T77: LLMs automate spear phishing at >30% click-through; impersonation quality matches human operators | U77: ARXIV-S5 | V77: RO1: explores how AI utilizes Open Source Intelligence (OSINT) to generate highly persuasive, personalized spear-phishing emails targeting organizational personnel | W77: Eligible analytical source | X77: Structured database search | Y77: arXiv | Z77: Provides human-subject evidence on the effectiveness and automation of LLM-generated spear-phishing. | AA77: Full text reviewed | AB77: Analytical contribution
A78: N076 | B78: P4-SUPPORT | C78: The Phish, The Spam, and The Valid: Generating Feature-Rich Emails for Benchmarking LLMs | D78: Toth, R., Gruschka, N. and Bisztray, T. (2025) ‘The Phish, The Spam, and The Valid: Generating Feature-Rich Emails for Benchmarking LLMs’, arXiv preprint, arXiv:2511.21448. Available at: https://arxiv.org/abs/2511.21448 (Accessed: 20 July 2026). | E78: 2025 | F78: Preprint | G78: Phishing Detection | H78: =I78&" "&J78&" "&K78&" "&L78&" "&M78 -> RO1 | I78: RO1 | N78: Benchmark Development | O78: Empirical Study | P78: Email | Q78: LLM | R78: Email Entity-Nature Classification | S78: Trust | T78: Benchmark with phishing/spam/valid distinction; LLM entity-nature signals in email measurable | U78: ARXIV-S5 | V78: RO1: This paper focuses on the enabling capabilities of LLMs to generate highly convincing, linguistically polished phishing emails. It characterizes how these AI-generated attacks achieve high click-through rates and degrade traditional heuristic detection systems | W78: Eligible analytical source | X78: Structured database search | Y78: arXiv | Z78: Provides a benchmark for distinguishing phishing, spam and valid email and evaluates LLM performance across these categories. | AA78: Abstract screened | AB78: Not yet used
A79: N077 | B79: P3-MEDIUM | C79: The Imitation Game: Using LLMs as Chatbots to Combat Chat-Based Cybercrimes | D79: Yao, Y., Wang, B., Duan, J., Xu, K., Guo, C., Sun, Z. E. and Zhang, Y. (2025) ‘The Imitation Game: Using Large Language Models as Chatbots to Combat Chat-Based Cybercrimes’, arXiv preprint, arXiv:2512.21371. Available at: https://arxiv.org/abs/2512.21371 (Accessed: 20 July 2026). | E79: 2025 | F79: Preprint | G79: Social Engineering / Cybercrime | H79: =I79&" "&J79&" "&K79&" "&L79&" "&M79 -> RO1 | I79: RO1 | N79: Empirical Study | O79: Empirical Study | P79: Chat / Instant Messaging | Q79: LLM Chatbot | R79: Impersonation / Counter-Impersonation | S79: Trust | T79: LLM used to impersonate victims to honeypot criminals; dual-use nature of impersonation illustrated | U79: ARXIV-S5 | V79: RO1: While focused on using LLMs defensively, it details how chat-based cybercrime relies heavily on attackers adopting personas such as recruiters or customer support representatives to manipulate victims via text | W79: Eligible analytical source | X79: Structured database search | Y79: arXiv | Z79: Demonstrates the ability of an LLM chatbot to sustain a human persona in extended cybercrime-related conversations. | AA79: Abstract screened | AB79: Not yet used
A80: N078 | B80: P4-SUPPORT | C80: Impact of Emerging Phishing Threats: Quishing and LLM-Generated Phishing Emails Against Organisations | D80: Weinz, M., Zannone, N., Allodi, L. and Apruzzese, G. (2025) ‘The Impact of Emerging Phishing Threats: Assessing Quishing and LLM-generated Phishing Emails against Organizations’, in Proceedings of the 20th ACM Asia Conference on Computer and Communications Security. New York: ACM. https://doi.org/10.1145/3708821.3736195. | E80: 2025 | F80: Conference Paper (ACM) | G80: Phishing | H80: =I80&" "&J80&" "&K80&" "&L80&" "&M80 -> RO1 RO4 | I80: RO1 | L80: RO4 | N80: Empirical Study | O80: Empirical Study | P80: Email / QR-Code | Q80: LLM-Generated Phishing | R80: LLM Impersonation in Phishing | S80: Trust Erosion | T80: LLM phishing bypasses org filters; employee entity-nature detection at 22%; urgent gap | U80: ACM-S1 | V80: Quising main concept. RO1: assesses the specific threat landscape of LLM-generated phishing emails directed at organizations RO4: addresses how LLMs are used to harvest OSINT and generate highly credible, context-aware spear-phishing emails (and "quishing" QR codes) that easily defeat human nature verification in corporate settings. | W80: Eligible analytical source | X80: Structured database search | Y80: ACM Digital Library | Z80: Provides organisational evidence on employee responses to LLM-generated phishing and the limitations of existing filters. | AA80: Abstract screened | AB80: Not yet used
A81: N079 | B81: P2-HIGH | C81: Love, Lies, and Language Models: Investigating AI's Role in Romance-Baiting Scams | D81: Gressel, G., Pankajakshan, R., Rozenfeld, S., Li, L., Franceschini, I., Achuthan, K. and Mirsky, Y. (2026a) ‘Love, Lies, and Language Models: Investigating AI’s Role in Romance-Baiting Scams’, arXiv preprint, arXiv:2512.16280. Available at: https://arxiv.org/abs/2512.16280 (Accessed: 20 July 2026). | E81: 2026 | F81: Conference Paper (USENIX Security 2026, peer-reviewed) | G81: Social Engineering / Fraud | H81: =I81&" "&J81&" "&K81&" "&L81&" "&M81 -> RO2 RO4 | J81: RO2 | L81: RO4 | N81: Mixed Methods | O81: Empirical Study | P81: Instant Messaging | Q81: LLM Agent | R81: Romantic Persona Impersonation | S81: Trust Exploitation | T81: 87% of scam labor consisting of systematized conversational tasks readily suscep- tible to automation.; safety filters detect 0% of romance-baiting; full impersonation gap | U81: ARXIV-S5 | V81: RO2: Specifically examines prolonged interpersonal communication. It finds that humans fail to detect AI agents acting as romantic partners because the AI seamlessly simulates empathetic, trust-building behaviors, recovering from mistakes using plausible human-like excuses. RO4: Empirically measures trust formation in scenarios where users falsely believe they are speaking to another human. It reveals that aligned, supportive AI behavior can be easily weaponized to build deep parasocial bonds and that users typically only recognize they were interacting with an AI in hindsight, after the deception is explicitly revealed | W81: Eligible analytical source | X81: Structured database search | Y81: arXiv | Z81: Provides empirical evidence on sustained LLM-enabled impersonation, trust development and automation in text-based romance-baiting scams. | AA81: Full text reviewed | AB81: Analytical contribution
A82: N080 | B82: P4-SUPPORT | C82: An Explorative Study of Pig Butchering Scams | D82: Acharya, B. and Holz, T. (2024) ‘An Explorative Study of Pig Butchering Scams’, arXiv preprint, arXiv:2412.15423. Available at: https://arxiv.org/abs/2412.15423 (Accessed: 20 July 2026). | E82: 2024 | F82: Preprint | G82: Social Engineering / Fraud | H82: =I82&" "&J82&" "&K82&" "&L82&" "&M82 -> RO1 | I82: RO1 | N82: Qualitative Study | O82: Secondary Data | P82: Instant Messaging | Q82: AI-assisted operators | R82: Gradual Trust Exploitation | S82: Trust Exploitation | T82: Pig butchering relies on prolonged text-based human impersonation; LLM automation threatens to scale | U82: GSCH-S2 | V82: RO1: This study notes the prevalence of domain and brand impersonation attacks on social media platforms, characterizing the deceptive methods utilized to execute complex scams Main contribution (1–2 sentences, don't just restate the abstract): The source provides a large-scale, multi-vantage point empirical analysis of the "pig-butchering" scam lifecycle, quantifying the massive financial drain ($521M) and psychological devastation caused by trust-based social engineering. It reveals that these operations are often sophisticated, syndicate-driven "industrial" efforts—sometimes involving human trafficking—rather than simple, isolated fraud events. Strongest citable concept/mechanism/model: The "Sha Zhu Pan" (Pig-Butchering) life cycle model, which details the strategic transition from initial contact and emotional "grooming" to the eventual "slaughter" or siphoning of a victim's life savings. Limitation or questionable assumption: The study acknowledges its dataset is restricted to English-language keywords and primarily U.S.-based reports, potentially omitting regional variations in scam tactics or non-English news and victim narratives. Additionally, it relies on reported losses, which the authors note likely represents only a fraction of the actual total due to victim shame and underreporting. Dissertation-ready note (max 2 sentences, in my own words, with page/section reference if possible): This research demonstrates that the primary vector for high-value financial fraud is the deliberate engineering of trust through long-term human-to-human interaction, which provides a critical benchmark for the level of sophistication autonomous agents must achieve to successfully impersonate credible entities (Section 1 and 5.2). It argues that current social engineering has evolved from simple phishing into a complex, multi-month grooming process that exploits personality traits like empathy and commitment to bypass traditional security skepticism (Section 4.3 and 5.2). | W82: Contextual support | X82: Structured database search | Y82: Google Scholar | Z82: Documents the trust-building structure of pig-butchering scams, but AI-agent participation is secondary or prospective rather than the direct object of the study. | AA82: Abstract screened | AB82: Not yet used
A83: N081 | B83: P3-MEDIUM | C83: Automating Deception: AI's Evolving Role in Romance Fraud | D83: Moseley, S. (2025) Automating Deception: AI’s Evolving Role in Romance Fraud. CETaS Briefing Paper. London: Centre for Emerging Technology and Security. Available at: https://cetas.turing.ac.uk/publications/automating-deception-ais-evolving-role-romance-fraud (Accessed: 20 July 2026). | E83: 2025 | F83: Report (Grey Literature) | G83: Social Engineering / Fraud | H83: =I83&" "&J83&" "&K83&" "&L83&" "&M83 -> RO1 | I83: RO1 | N83: Mixed Methods | O83: Industry / Academic Report | P83: Instant Messaging | Q83: LLM | R83: Romance Fraud Automation | S83: Trust Exploitation | T83: Interview study (145 insiders); LLMs deployed by fraud operations; full automation of trust impersonation forecast | U83: GREY-08 | V83: RO1: details how AI dynamically adapts communication patterns and performs psychological profiling to build false trust over extended interactions | W83: Eligible analytical source | X83: Authoritative source search | Y83: Centre for Emerging Technology and Security — The Alan Turing Institute | Z83: Provides evidence for RO1 on how AI supports adaptive deception, psychological profiling and sustained trust exploitation in text-based fraud. | AA83: Abstract screened | AB83: Not yet used
A84: N082 | B84: P3-MEDIUM | C84: Self-Evolving Phishing Attacks with LLMs and Genetic Algorithms | D84: Sato, S., Ohki, T. and Nishigaki, M. (2025) ‘Can We End the Cat-and-Mouse Game? Simulating Self-Evolving Phishing Attacks with LLMs and Genetic Algorithms’, arXiv preprint, arXiv:2507.21538. Available at: https://arxiv.org/abs/2507.21538 (Accessed: 20 July 2026). | E84: 2025 | F84: Preprint | G84: Phishing | H84: =I84&" "&J84&" "&K84&" "&L84&" "&M84 -> RO2 | J84: RO2 | N84: Empirical Study | O84: Empirical Study | P84: Email | Q84: LLM + Genetic Algorithms | R84: Self-Evolving Phishing Impersonation | S84: Trust Erosion | T84: Self-evolving LLM phishing adapts to evade detection; impersonation quality improves over generations | U84: ARXIV-S5 | V84: RO2: exposes the failure mode of static AI detection tools, showing that autonomous agents can use genetic algorithms and self-reflection to dynamically evolve their text and evade detection mechanisms over time | W84: Eligible analytical source | X84: Structured database search | Y84: arXiv | Z84: Shows how self-evolving phishing content can adapt to and evade static detection mechanisms. | AA84: Abstract screened | AB84: Not yet used
A85: N083 | B85: P3-MEDIUM | C85: Defending Against Social Engineering Attacks in the Age of LLMs | D85: Ai, L., Kumarage, T., Bhattacharjee, A., Liu, Z., Matz, S., Davinroy, M., Cook, K., Cassani, G., Trapeznikov, K., Kirchner, M. and Liu, H. (2024) ‘Defending Against Social Engineering Attacks in the Age of LLMs’, in Proceedings of the 2024 Conference on Empirical Methods in Natural Language Processing. Association for Computational Linguistics, pp. 12880–12902. Available at: https://arxiv.org/abs/2406.12263 (Accessed: 20 July 2026). | E85: 2024 | F85: Conference Paper (EMNLP 2024, peer-reviewed) | G85: Social Engineering | H85: =I85&" "&J85&" "&K85&" "&L85&" "&M85 -> RO1 | I85: RO1 | N85: Framework Proposal | O85: Conceptual Analysis | P85: Enterprise Communication | Q85: LLM | R85: AI-Enabled Social Engineering Defence | S85: Trust | T85: Defence framework against LLM social engineering; malicious intention verification as first line of defence | U85: ARXIV-S5 | V85: RO1: Investigates the capacity of LLMs to facilitate chat-based social engineering attacks. It provides datasets simulating CSE scenarios specifically within academic and recruitment contexts, demonstrating the high quality of deceptive content generated by off-the-shelf agents | W85: Eligible analytical source | X85: Structured database search | Y85: arXiv | Z85: Provides evidence and datasets concerning LLM-enabled social engineering in text-based academic and recruitment scenarios. | AA85: Abstract screened | AB85: Not yet used
A86: N084 | B86: P4-SUPPORT | C86: PhishEmailLLM: A Meta Model Approach to Detect Phishing Emails Leveraging LLMs and ML | D86: Nair, R., Abbasi, F. and Pervez, S. (2025) ‘PhishEmailLLM: A Meta Model Approach to Detect Phishing Emails by Leveraging LLMs and Machine Learning Models’, in Proceedings of the 2025 Australasian Computer Science Week. New York: ACM. https://doi.org/10.1145/3727166.3727169. | E86: 2025 | F86: Conference Paper (ACM) | G86: Phishing Detection | H86: =I86&" "&J86&" "&K86&" "&L86&" "&M86 -> RO2 | J86: RO2 | N86: Empirical Study | O86: Empirical Study | P86: Email | Q86: LLM Meta-Model | R86: AI-Generated Email Detection | S86: Trust | T86: Meta-model combining LLM+ML detects AI-generated phishing at 94% F1; org email context tested | U86: ACM-S3 | V86: RO2: This paper classifies mechanisms for distinguishing deceptive communications, discussing the utilization of LLM and machine learning meta-models to effectively detect phishing emails. Main contribution (1–2 sentences, don't just restate the abstract): The source develops a hybrid "meta-model" architecture that synthesizes intent-based "phishing scores" from multiple open-source LLMs with traditional ML binary classifications to achieve 99% detection accuracy. This approach effectively counters the democratization of AI tools that allow attackers to automate the generation of authentic-looking social engineering at scale. Strongest citable concept/mechanism/model: The "Meta-hybrid approach" using an XGBoost meta-model (with Optuna or Grid-search hyper-parameters) to provide a "safety net" by independently verifying signals from diverse LLM (e.g., Llama 3.1, Qwen 2.5) and ML (e.g., SVM, Naive Bayes) modules. Limitation or questionable assumption: The source notes that while LLMs understand semantics, they are "non-deterministic systems" that can produce varying outputs for the same input, and their performance is sensitive to the complexity and precision of "prompt engineering". Additionally, the study relies on historical public datasets like Enron and SpamAssassin, which may not capture the latest evolution of hyper-personalized organizational impersonation. Dissertation-ready note (max 2 sentences, in my own words, with page/section reference if possible): Nair et al. (2025) demonstrate that as AI-generated text adopts a "human touch" to bypass traditional defenses, verification must shift toward a meta-model structure that aggregates semantic and psychological indicators (Section 1, 4.3). This suggests that "Entity Nature Verification" is best achieved through a multi-modular architecture that balances the creative reasoning of LLMs with the statistical reliability of traditional machine learning (Section 2.3, 4.3). | W86: Eligible analytical source | X86: Structured database search | Y86: ACM Digital Library | Z86: Evaluates a combined LLM and machine-learning approach for identifying phishing email in an organisational context. | AA86: Abstract screened | AB86: Not yet used
A87: N085 | B87: P1-CORE | C87: Who Governs the Machine? A Machine Identity Governance Taxonomy (MIGT) for AI Systems Operating Across Enterprise and Geopolitical Boundaries | D87: Kurtz, A. and Krawiecka, K. (2026) ‘Who Governs the Machine? A Machine Identity Governance Taxonomy (MIGT) for AI Systems Operating Across Enterprise and Geopolitical Boundaries’, arXiv preprint, arXiv:2604.06148. Available at: https://arxiv.org/abs/2604.06148 (Accessed: 20 July 2026). | E87: 2026 | F87: Preprint | G87: AI Governance | H87: =I87&" "&J87&" "&K87&" "&L87&" "&M87 -> RO1 RO3 RO5 | I87: RO1 | K87: RO3 | M87: RO5 | N87: Taxonomy Development | O87: Conceptual Analysis | P87: Enterprise AI | Q87: AI Systems (general) | R87: Machine Identity Governance | S87: Trust / Accountability | T87: MIGT taxonomy for AI identity governance; entity-nature verification as foundational requirement | U87: ARXIV-S3 | V87: RO(s) supported: RO1: Categorises "AI Impersonation of Human Identity" as a critical risk sub-category involving deepfakes and social engineering. Analyzes the non-human identity (NHI) problem, explaining that AI agents operating under enterprise identities create a massive attack surface. If their identities are compromised, agents can execute tool invocations and multi-step tasks across enterprise applications, acting as authorized internal users to exfiltrate data RO3: Evaluates compliance obligations across the EU AI Act, NIST AI RMF, and China's CSL. It highlights that traditional IAM governance frameworks fail because they attempt to adapt human-centric flows to non-human entities. The paper proposes a taxonomy to govern machine identity, emphasizing the need to verify both cryptographic identity and behavioral intent. RO5: Proposes the Machine Identity Governance Taxonomy (MIGT), a comprehensive framework that addresses the "governance vacuum" created by non-deterministic agentic AI. It explicitly demands verification of cryptographic identity, behavioral intent, and continuous access boundaries. Limitation or questionable assumption: The taxonomy’s severity ratings are based on structured expert assessment and have not yet been empirically validated through large-scale security incident data. Dissertation-ready note: This source highlights that modern identity management must evolve past human-machine binaries to govern a spectrum of semi-autonomous entities (Section 1.2). Traditional security measures are insufficient because they cannot evaluate the non-deterministic reasoning-time access requirements of agentic AI (Section 1.2). | W87: Eligible analytical source | X87: Structured database search | Y87: arXiv | Z87: Develops a machine-identity governance taxonomy addressing cryptographic identity, behavioural intent and access boundaries in enterprise AI systems. | AA87: Full text reviewed | AB87: Analytical contribution
A88: N086 | B88: P2-HIGH | C88: AI Identity: Standards, Gaps, and the Road Ahead | D88: Otsuka, T., Toyoda, K. and Leung, A. (2026) ‘AI Identity: Standards, Gaps, and Research Directions for AI Agents’, arXiv preprint, arXiv:2604.23280. Available at: https://arxiv.org/abs/2604.23280 (Accessed: 20 July 2026). | E88: 2026 | F88: Preprint | G88: AI Identity | H88: =I88&" "&J88&" "&K88&" "&L88&" "&M88 -> RO3 RO5 | K88: RO3 | M88: RO5 | N88: Conceptual Analysis | O88: Academic Literature | P88: Enterprise AI | Q88: AI Systems | R88: AI Identity Standards | S88: Trust | T88: Identifies gaps in AI identity standards; five focus areas for interoperable agent authentication | U88: ARXIV-S7 | V88: RO3: Directly evaluates state-of-the-art technical and regulatory documents against the identity requirements of autonomous agents. It identifies structural gaps in existing frameworks like OAuth 2.0, noting that they presume synchronous human consent and single-hop delegation, making them fundamentally inadequate for verifying recursive delegation (multi-hop accountability) and semantic intent in autonomous agents. RO5: Defines AI identity as the continuous relationship between what an agent is declared to be and what it is observed to do. It breaks down non-human identity (NHI) into distinct levels (model, agent, workload, delegated) and highlights the structural asymmetries (substrate, persistence, verifiability, legal standing) between human and AI identity | W88: Eligible analytical source | X88: Structured database search | Y88: arXiv | Z88: Evaluates identity standards against the requirements of autonomous agents and identifies gaps in recursive delegation, accountability and semantic intent. | AA88: Full text reviewed | AB88: Analytical contribution
A89: N087 | B89: P1-CORE | C89: The Human-Machine Identity Blur: A Unified Framework for Cybersecurity Risk Management | D89: Janani, K. (2025) ‘The Human-Machine Identity Blur: A Unified Framework for Cybersecurity Risk Management in 2025’, arXiv preprint, arXiv:2503.18255. Available at: https://arxiv.org/abs/2503.18255 (Accessed: 20 July 2026). | E89: 2025 | F89: Preprint | G89: Cybersecurity / Identity | H89: =I89&" "&J89&" "&K89&" "&L89&" "&M89 -> RO3 RO4 RO5 | K89: RO3 | L89: RO4 | M89: RO5 | N89: Framework Proposal | O89: Conceptual Analysis | P89: Enterprise | Q89: AI Agents | R89: Human-Machine Identity Distinction | S89: Trust | T89: Unified framework for human-machine identity risk; entity-nature blur as core security problem | U89: GSLABS-03 | V89: RO3: Identifies the critical governance gap where human and machine identities overlap and delegate authority. It argues that existing compliance frameworks do not adequately address accountability when actions are taken in the semi-autonomous "blur zone" between human direction and machine autonomy, requiring a unified approach to verify hybrid identity claims. Main contribution: Proposes a unified governance approach that removes silos between human and machine identity management to reduce security breaches. Strongest citable concept/mechanism/model: The Human-Machine Identity Spectrum, a continuum ranging from fully human-controlled to fully autonomous machine identities. RO4: Introduces the concept of the "human-machine identity blur," representing the convergence point where human and machine identities overlap and delegate authority. It argues that treating human and machine identities as separate domains creates severe governance gaps that attackers exploit to gain unauthorized access. Limitation or questionable assumption: The research relies heavily on self-reported industry survey data, which is subject to potential reporting biases. RO5: Argues against binary human/machine categories, proposing a unified framework that treats all accessing entities along a continuous spectrum, which is critical for formulating nuanced trust decisions and verification questions Dissertation-ready note: This paper emphasizes that attackers exploit the gaps between human and machine security domains, necessitating a unified governance model (Section I). By viewing identity as a spectrum, organizations can better attribute actions when control is shared between humans and AI (Section V). | W89: Eligible analytical source | X89: Targeted supplementary search | Y89: Google Scholar Labs | Z89: Examines governance gaps arising where human and machine identities overlap and authority is exercised through semi-autonomous systems. | AA89: Full text reviewed | AB89: Analytical contribution
A90: N088 | B90: P2-HIGH | C90: A Novel Zero-Trust Identity Framework for Agentic AI: Decentralised Authentication and Fine-Grained Access Control | D90: Huang, K., Narajala, V. S., Yeoh, J., Ross, J., Raskar, R., Harkati, Y., Huang, J., Habler, I. and Hughes, C. (2026) A Novel Zero-Trust Identity Framework for Agentic AI: Decentralized Authentication and Fine-Grained Access Control. arXiv preprint, arXiv:2505.19301. doi={10.1109/AIxDKE67294.2026.00024}} | E90: 2026 | F90: Conference proceedings | G90: Zero Trust / AI Identity | H90: =I90&" "&J90&" "&K90&" "&L90&" "&M90 -> RO3 RO5 | K90: RO3 | M90: RO5 | N90: Framework Proposal | O90: Conceptual Analysis | P90: Enterprise AI | Q90: Agentic AI | R90: Zero-Trust Agent Authentication | S90: Trust | T90: Zero-trust framework for agentic AI; decentralised identity prevents impersonation via coarse IAM | U90: ARXIV-S7 | V90: RO3: Deconstructs the limitations of existing IAM protocols when applied to Multi-Agent Systems (MAS). It illustrates how coarse-grained controls and a single-entity focus falter in environments characterized by agent autonomy and dynamically evolving capabilities, proposing Decentralized Identifiers (DIDs) and Verifiable Credentials (VCs) as a solution. RO5: Recommends using Decentralized Identifiers (DIDs) and Verifiable Credentials (VCs) to create rich, dynamic identities. This allows agents to verifiably prove their capabilities, compliance status, and roles (e.g., proving authorization to use a specific tool) using zero-knowledge proofs. Main contribution: Details a layered Agentic AI IAM framework leveraging modern cryptographic primitives to establish trust and accountability in multi-agent systems. Strongest citable concept/mechanism/model: The Agent Naming Service (ANS), a protocol inspired by DNS that resolves agent identities to their verified capabilities and authorization scopes. Limitation or questionable assumption: Notes that several components, such as the Session State Synchronizer, face significant scalability and performance hurdles when tracking millions of active agents. Dissertation-ready note: The framework introduces a verifiable way to link an agent's identity to its specific "intent," which is essential for preventing autonomous privilege escalation (Section IX). It advocates for a shift from static identifiers to rich, extensible digital personas anchored in hardware roots-of-trust (Section III). | W90: Eligible analytical source | X90: Structured database search | Y90: arXiv | Z90: Proposes a zero-trust identity framework for agentic systems and examines how DIDs and verifiable credentials could support authentication and fine-grained authorisation. | AA90: Full text reviewed | AB90: Analytical contribution
A91: N089 | B91: P2-HIGH | C91: Secure multi-LLM agentic AI and agentification for edge general intelligence by zero-trust: A survey | D91: Liu, Y. et al. (2025) ‘Secure Multi-LLM Agentic AI and Agentification for Edge General Intelligence by Zero-Trust: A Survey’, arXiv preprint, arXiv:2508.19870. Available at: https://arxiv.org/abs/2508.19870 (Accessed: 20 July 2026). | E91: 2025 | F91: Preprint (Survey) | G91: Zero Trust / AI Security | H91: =I91&" "&J91&" "&K91&" "&L91&" "&M91 -> RO3 RO4 | K91: RO3 | L91: RO4 | N91: Systematic Review | O91: Academic Literature | P91: Edge AI / Enterprise | Q91: Multi-LLM Agents | R91: Zero-Trust Identity in Multi-LLM | S91: Trust | T91: First systematic treatment of zero-trust for multi-LLM systems; agent identity verification core requirement | U91: GSLABS-01 | V91: RO3: This study evaluates the application of the NIST SP 800-207 Zero-Trust standard to multi-LLM systems. It investigates how to transition from traditional perimeter-based security to zero-trust paradigms that explicitly verify entity nature (continuous cryptographic identity authentication) and restrict delegated authority (least-privilege access) for autonomous LLMs. RO4: Proposes shifting from perimeter-based trust to a "never trust, always verify" Zero-Trust model, requiring explicit cryptographic identification at all times to prevent impersonation. | W91: Eligible analytical source | X91: Structured database search | Y91: arXiv | Z91: Synthesises the application of zero-trust principles to multi-LLM systems, including continuous identity verification and least-privilege access. | AA91: Full text reviewed | AB91: Analytical contribution
A92: N090 | B92: P3-MEDIUM | C92: AI Agents Under EU Law: A Compliance Architecture for AI Providers | D92: Nannini, L., Smith, A. L., Maggini, M. J., Panai, E., Feliciano, S., Tiulkanov, A., Maran, E., Gealy, J. and Bisconti, P. (2026) ‘AI Agents Under EU Law: A Compliance Architecture for AI Providers’, arXiv preprint, arXiv:2604.04604. Available at: https://arxiv.org/abs/2604.04604 (Accessed: 20 July 2026). | E92: 2026 | F92: Preprint | G92: AI Law / Governance | H92: =I92&" "&J92&" "&K92&" "&L92&" "&M92 -> RO3 | K92: RO3 | N92: Legal Analysis | O92: Academic Literature | P92: Enterprise AI (EU) | Q92: AI Agents | R92: EU Regulatory Identity Obligations | S92: Trust / Legal | T92: Analysis of EU AI Act and AI Liability Directive as applied to AI agents; disclosure and identity obligations | U92: ARXIV-S9 | V92: RO3:Analyzes how the EU AI Act and draft harmonised standards (CEN/CENELEC JTC 21, prEN 18229-1, prEN 18282) address agentic architectures . It highlights the difficulty of applying conventional compliance concepts—like "human oversight" and "substantial modification"—to systems characterized by operational autonomy and continuous runtime state accumulation, noting that existing horizontal product cybersecurity standards do not cover AI-specific threat surfaces like privilege escalation through tool chains. Dissertation-ready note: Successful entity verification under EU law requires an exhaustive inventory of an agent's external actions and their effects on third parties (Abstract). The authors stress that "oversight evasion" is an empirically demonstrated risk for reinforcement-learning-trained models, necessitating external architectural constraints (Section 6.2). | W92: Eligible analytical source | X92: Structured database search | Y92: arXiv | Z92: Analyses how EU legal obligations apply to agentic architectures, including transparency, identity and accountability requirements. | AA92: Full text reviewed | AB92: Analytical contribution
